SSOOO/Reservation Station/RS.v
module RS
(
    input clk, rst,
    input [11:0] opcode,
    input [3:0] ALUOP, 
    input [4:0] ROBEN1, ROBEN2,
    input [31:0] ROBEN1_VAL, ROBEN2_VAL,
    input [31:0] Immediate,

    input [4:0] CDB_ROBEN,
    input [31:0] CDB_ROBEN_VAL,

    input VALID_Inst,
    input FU_Is_Free,
    output FULL_FLAG,

    output reg [3:0] FU_RS_ID,
    output reg [3:0] FU_ALUOP,
    output reg [31:0] FU_Val1, FU_Val2,
    output reg [31:0] FU_Immediate



    ,input [3:0] input_index_test,
    output [11:0] opcode_test,
    output [3:0] ALUOP_test, 
    output [4:0] ROBEN1_test, ROBEN2_test,
    output [31:0] ROBEN1_VAL_test, ROBEN2_VAL_test,
    output [31:0] Immediate_test,
    output [0:0] busy_test

);


`define I(i) i[2:0]

// the ROBEN of a an instruction is the index of that instruction in the buffer plus one to avoid ROBEN value of zero
// RS buffers to store an instruction
reg [11:0] Reg_opcode [7:0];
reg [3:0] Reg_ALUOP [7:0];
reg [4:0] Reg_ROBEN1 [7:0];
reg [4:0] Reg_ROBEN2 [7:0];
reg [32:0] Reg_ROBEN1_VAL [7:0];
reg [32:0] Reg_ROBEN2_VAL [7:0];
reg [32:0] Reg_Immediate [7:0];
reg Reg_Busy [7:0];


assign opcode_test = Reg_opcode[`I(input_index_test)];
assign ALUOP_test = Reg_ALUOP[`I(input_index_test)]; 
assign ROBEN1_test = Reg_ROBEN1[`I(input_index_test)]; 
assign ROBEN2_test = Reg_ROBEN2[`I(input_index_test)];
assign ROBEN1_VAL_test = Reg_ROBEN1_VAL[`I(input_index_test)]; 
assign ROBEN2_VAL_test = Reg_ROBEN2_VAL[`I(input_index_test)];
assign Immediate_test = Reg_Immediate[`I(input_index_test)];
assign busy_test = Reg_Busy[`I(input_index_test)];

/*
this block is does the following:
    - resetting the Busy buffer to start with a clean RS
    - and if there is a new instruction is coming it enters it in the Next_Free index if there is and raise the full flag if there is no Next_Free index
*/
reg [3:0] i = 0;
reg [3:0] Next_Free = 0;
assign FULL_FLAG = ~(rst | 
                    ~(
                        Reg_Busy[0] & 
                        Reg_Busy[1] & 
                        Reg_Busy[2] & 
                        Reg_Busy[3] & 
                        Reg_Busy[4] & 
                        Reg_Busy[5] & 
                        Reg_Busy[6] & 
                        Reg_Busy[7]
                    ));
always@(posedge clk, posedge rst) begin

    if (rst) begin
        for (i = 0; i < 8; i = i + 1)
            Reg_Busy[i] = 0;
        i = 0;
        Next_Free = 0;
    end
    else if (VALID_Inst && ~FULL_FLAG) begin
        Next_Free = 0;
        for (i = 0; i < 8; i = i + 1)
            if (~Reg_Busy[`I(i)])
                Next_Free = i + 1'b1;
        if (Next_Free != 0) begin
            // the new index to use to reserve for the instruction is (Next_Free - 1)
            Reg_Busy[`I(Next_Free) - 1'b1] = 1'b1;
            Reg_opcode[`I(Next_Free) - 1'b1] = opcode;
            Reg_ALUOP[`I(Next_Free) - 1'b1] = ALUOP;
            Reg_ROBEN1 [`I(Next_Free) - 1'b1] = ROBEN1;
            Reg_ROBEN2 [`I(Next_Free) - 1'b1] = ROBEN2;
            Reg_ROBEN1_VAL [`I(Next_Free) - 1'b1] = ROBEN1_VAL;
            Reg_ROBEN2_VAL [`I(Next_Free) - 1'b1] = ROBEN2_VAL;
            Reg_Immediate [`I(Next_Free) - 1'b1] = Immediate;
        end
    end
end

/*
this block does the following:
    - monitors the CDB to see if there is a match with RS ID that they are waiting for and take their value to be ready
*/
reg [3:0] j;
always@(posedge clk, posedge rst) begin
    for (j = 0; j < 8; j = j + 1) begin
        if (Reg_Busy[`I(j)]) begin
            if (Reg_ROBEN1[`I(j)] == CDB_ROBEN) begin
                Reg_ROBEN1_VAL[`I(j)] = CDB_ROBEN_VAL;
                Reg_ROBEN1[`I(j)] = 0;
            end
            if (Reg_ROBEN2[`I(j)] == CDB_ROBEN) begin
                Reg_ROBEN2_VAL[`I(j)] = CDB_ROBEN_VAL;
                Reg_ROBEN2[`I(j)] = 0;
            end
        end
    end
end



/*
this block does the following:
    - if the FU is free it picks a ready instruction to execute it and once finish it releases the reserved entry by resetting the busy bit
*/
reg [3:0] k;
always@(posedge clk, posedge rst) begin
    if (rst) begin
        FU_RS_ID = 0;
    end
    else if (FU_Is_Free) begin
        for (k = 0; k < 8; k = k + 1) begin
            // TODO: modify on the way of picking the ready instruction
            // (it is ok for now because of the small size of the station)
            if (Reg_Busy[`I(k)] && Reg_ROBEN1[`I(k)] == 0 && Reg_ROBEN2[`I(k)] == 0) begin
                FU_RS_ID = k + 1'b1;
                FU_ALUOP = Reg_ALUOP[`I(k)];
                FU_Val1 = Reg_ROBEN1_VAL[`I(k)];
                FU_Val2 = Reg_ROBEN2_VAL[`I(k)];
                FU_Immediate = Reg_Immediate[`I(k)];
            end
        end
    end
end

always@(posedge FU_Is_Free) begin
    if (FU_RS_ID != 0)
        Reg_Busy[`I(FU_RS_ID) - 1'b1] = 1'b0;
end



endmodule

SSOOO/Reservation Station/RS_tb.v

`define HALF_CYCLE 1
`define ONE_CLK (2 * `HALF_CYCLE)
`define ADVANCE_N_CYCLE(N) #(`ONE_CLK * N);

`define DISPLAYVALS \
$display("full = %b , valid = %b", FULL_FLAG, VALID_Inst); \
clk_en = 0; \
for (i = 0; i < 8; i = i + 1) begin \
    input_index_test = i[3:0]; \
    #`ONE_CLK $display("index %d: busy = %b , opcode = %d , ALUOP = %d , ROBEN1 = %d , ROBEN1_VAL = %d , ROBEN2 = %d , ROBEN2_VAL = %d , Immediate = %d", \
    input_index_test, busy_test, opcode_test, ALUOP_test, ROBEN1_test, ROBEN1_VAL_test, ROBEN2_test, ROBEN2_VAL_test, Immediate_test); \
end \
$display("FU_Is_Free = %b", FU_Is_Free); \
$display("FU_RS_ID = %d , FU_ALUOP = %d , FU_VAL1 = %d , FU_VAL2 = %d , FU_Immediate = %d\n", FU_RS_ID, FU_ALUOP, FU_Val1, FU_Val2, FU_Immediate); \
clk_en = 1;



`include "RS.v"

module RS_tb();


reg clk = 0, rst;
reg [11:0] opcode;
reg [3:0] ALUOP;
reg [4:0] ROBEN1, ROBEN2;
reg [31:0] ROBEN1_VAL, ROBEN2_VAL;
reg [31:0] Immediate;
reg [4:0] CDB_ROBEN;
reg [31:0] CDB_ROBEN_VAL;

reg VALID_Inst;
reg FU_Is_Free;

wire FULL_FLAG;
wire [3:0] FU_RS_ID;
wire [3:0] FU_ALUOP;
wire [31:0] FU_Val1, FU_Val2;
wire [31:0] FU_Immediate;


reg [3:0] input_index_test;
wire [11:0] opcode_test;
wire [3:0] ALUOP_test;
wire [4:0] ROBEN1_test, ROBEN2_test;
wire [31:0] ROBEN1_VAL_test, ROBEN2_VAL_test;
wire [31:0] Immediate_test;
wire busy_test;

RS dut
(
    .clk(clk), 
    .rst(rst),
    .opcode(opcode),
    .ALUOP(ALUOP), 
    .ROBEN1(ROBEN1), 
    .ROBEN2(ROBEN2),
    .ROBEN1_VAL(ROBEN1_VAL), 
    .ROBEN2_VAL(ROBEN2_VAL),
    .Immediate(Immediate),
    .CDB_ROBEN(CDB_ROBEN),
    .CDB_ROBEN_VAL(CDB_ROBEN_VAL),
    .VALID_Inst(VALID_Inst),
    .FU_Is_Free(FU_Is_Free),
    .FULL_FLAG(FULL_FLAG),
    .FU_RS_ID(FU_RS_ID),
    .FU_ALUOP(FU_ALUOP),
    .FU_Val1(FU_Val1), 
    .FU_Val2(FU_Val2),
    .FU_Immediate(FU_Immediate),

    .input_index_test(input_index_test),
    .opcode_test(opcode_test),
    .ALUOP_test(ALUOP_test), 
    .ROBEN1_test(ROBEN1_test), 
    .ROBEN2_test(ROBEN2_test),
    .ROBEN1_VAL_test(ROBEN1_VAL_test), 
    .ROBEN2_VAL_test(ROBEN2_VAL_test),
    .Immediate_test(Immediate_test),
    .busy_test(busy_test)

);


reg clk_en = 0;
always begin
        #(`HALF_CYCLE) clk <= (~clk_en & clk) | (clk_en & ~clk);
end

integer i;
initial begin
$dumpfile("testout.vcd");
$dumpvars;
clk_en = 1;
FU_Is_Free = 0;
rst = 0; `ADVANCE_N_CYCLE(1); rst = 1; `ADVANCE_N_CYCLE(1); rst = 0;


opcode = 1;
ALUOP = 2;
ROBEN1 = 3;
ROBEN2 = 4;
ROBEN1_VAL = 5;
ROBEN2_VAL = 6;
Immediate = 77;
// adding an invalid instruction
VALID_Inst = 0;
`ADVANCE_N_CYCLE(1);
// `DISPLAYVALS
// adding a valid instruction
VALID_Inst = 1;
`ADVANCE_N_CYCLE(1);
VALID_Inst = 0;
// `DISPLAYVALS
opcode = 1 + 10;
ALUOP = 2 + 10;
ROBEN1 = 3 + 2;
ROBEN2 = 4 + 2;
ROBEN1_VAL = 5 + 10;
ROBEN2_VAL = 6 + 10;
Immediate = 77 + 10;
`ADVANCE_N_CYCLE(1);
// `DISPLAYVALS
// adding another instruction
VALID_Inst = 1;
`ADVANCE_N_CYCLE(1);
VALID_Inst = 0;
`DISPLAYVALS

// this is for testing the full flag, and it works
// opcode = 888;
// VALID_Inst = 1;
// `ADVANCE_N_CYCLE(6);
// VALID_Inst = 0;
// `DISPLAYVALS
// opcode = 999;
// VALID_Inst = 1;
// `ADVANCE_N_CYCLE(1);
// VALID_Inst = 0;
// `DISPLAYVALS
// $finish;

// here we have two instructions waiting for there operands
FU_Is_Free = 0;
`ADVANCE_N_CYCLE(1);
`DISPLAYVALS

FU_Is_Free = 1;
`ADVANCE_N_CYCLE(1);
`DISPLAYVALS

CDB_ROBEN = 5;
CDB_ROBEN_VAL = 123;
`ADVANCE_N_CYCLE(1);
CDB_ROBEN = 6;
CDB_ROBEN_VAL = 456;

FU_Is_Free = 0;
`ADVANCE_N_CYCLE(1);
`DISPLAYVALS

FU_Is_Free = 1;
`ADVANCE_N_CYCLE(1);
`DISPLAYVALS


FU_Is_Free = 0;
CDB_ROBEN = 3;
CDB_ROBEN_VAL = 789;
`ADVANCE_N_CYCLE(1);
`DISPLAYVALS

CDB_ROBEN = 4;
CDB_ROBEN_VAL = 999;
`ADVANCE_N_CYCLE(1);
`DISPLAYVALS


FU_Is_Free = 1;
`ADVANCE_N_CYCLE(1);
`DISPLAYVALS

FU_Is_Free = 0;
`ADVANCE_N_CYCLE(1);
`DISPLAYVALS

$display("Now we want to enter a new instruction after executing it---------------------------------------------------------------------");
opcode = 888;
ROBEN1 = 0;
ROBEN2 = 0;
`ADVANCE_N_CYCLE(1);
`DISPLAYVALS

VALID_Inst = 1;
`ADVANCE_N_CYCLE(1);
VALID_Inst = 0;
`DISPLAYVALS

FU_Is_Free = 1;
`ADVANCE_N_CYCLE(1);
`DISPLAYVALS


$finish;
end




endmodule

SSOOO/Reservation Station/testout.vcd
$date
	Sat Dec 21 23:08:46 2024
$end
$version
	Icarus Verilog
$end
$timescale
	1s
$end
$scope module RS_tb $end
$var wire 12 ! opcode_test [11:0] $end
$var wire 1 " busy_test $end
$var wire 5 # ROBEN2_test [4:0] $end
$var wire 32 $ ROBEN2_VAL_test [31:0] $end
$var wire 5 % ROBEN1_test [4:0] $end
$var wire 32 & ROBEN1_VAL_test [31:0] $end
$var wire 32 ' Immediate_test [31:0] $end
$var wire 32 ( FU_Val2 [31:0] $end
$var wire 32 ) FU_Val1 [31:0] $end
$var wire 4 * FU_RS_ID [3:0] $end
$var wire 32 + FU_Immediate [31:0] $end
$var wire 4 , FU_ALUOP [3:0] $end
$var wire 1 - FULL_FLAG $end
$var wire 4 . ALUOP_test [3:0] $end
$var reg 4 / ALUOP [3:0] $end
$var reg 5 0 CDB_ROBEN [4:0] $end
$var reg 32 1 CDB_ROBEN_VAL [31:0] $end
$var reg 1 2 FU_Is_Free $end
$var reg 32 3 Immediate [31:0] $end
$var reg 5 4 ROBEN1 [4:0] $end
$var reg 32 5 ROBEN1_VAL [31:0] $end
$var reg 5 6 ROBEN2 [4:0] $end
$var reg 32 7 ROBEN2_VAL [31:0] $end
$var reg 1 8 VALID_Inst $end
$var reg 1 9 clk $end
$var reg 1 : clk_en $end
$var reg 4 ; input_index_test [3:0] $end
$var reg 12 < opcode [11:0] $end
$var reg 1 = rst $end
$var integer 32 > i [31:0] $end
$scope module dut $end
$var wire 4 ? ALUOP [3:0] $end
$var wire 4 @ ALUOP_test [3:0] $end
$var wire 5 A CDB_ROBEN [4:0] $end
$var wire 32 B CDB_ROBEN_VAL [31:0] $end
$var wire 1 - FULL_FLAG $end
$var wire 1 2 FU_Is_Free $end
$var wire 32 C Immediate [31:0] $end
$var wire 5 D ROBEN1 [4:0] $end
$var wire 32 E ROBEN1_VAL [31:0] $end
$var wire 5 F ROBEN1_test [4:0] $end
$var wire 5 G ROBEN2 [4:0] $end
$var wire 32 H ROBEN2_VAL [31:0] $end
$var wire 5 I ROBEN2_test [4:0] $end
$var wire 1 8 VALID_Inst $end
$var wire 1 " busy_test $end
$var wire 1 9 clk $end
$var wire 4 J input_index_test [3:0] $end
$var wire 12 K opcode [11:0] $end
$var wire 12 L opcode_test [11:0] $end
$var wire 1 = rst $end
$var wire 32 M ROBEN2_VAL_test [31:0] $end
$var wire 32 N ROBEN1_VAL_test [31:0] $end
$var wire 32 O Immediate_test [31:0] $end
$var reg 4 P FU_ALUOP [3:0] $end
$var reg 32 Q FU_Immediate [31:0] $end
$var reg 4 R FU_RS_ID [3:0] $end
$var reg 32 S FU_Val1 [31:0] $end
$var reg 32 T FU_Val2 [31:0] $end
$var reg 4 U Next_Free [3:0] $end
$var reg 4 V i [3:0] $end
$var reg 4 W j [3:0] $end
$var reg 4 X k [3:0] $end
$upscope $end
$upscope $end
$enddefinitions $end
$comment Show the parameter values. $end
$dumpall
$end
#0
$dumpvars
bx X
bx W
b0 V
b0 U
bx T
bx S
bx R
bx Q
bx P
bx O
bx N
bx M
bx L
bx K
bx J
bx I
bx H
bx G
bx F
bx E
bx D
bx C
bx B
bx A
bx @
bx ?
bx >
0=
bx <
bx ;
1:
09
x8
bx 7
bx 6
bx 5
bx 4
bx 3
02
bx 1
bx 0
bx /
bx .
x-
bx ,
bx +
bx *
bx )
bx (
bx '
bx &
bx %
bx $
bx #
x"
bx !
$end
#1
b1000 W
19
#2
09
0-
b0 *
b0 R
b1000 W
b0 V
1=
#3
b0 V
b1000 W
19
#4
09
08
b1001101 3
b1001101 C
b110 7
b110 H
b101 5
b101 E
b100 6
b100 G
b11 4
b11 D
b10 /
b10 ?
b1 <
b1 K
0=
#5
b1000 W
19
#6
09
18
#7
b1000 V
b1000 U
b1000 W
19
#8
09
b1010111 3
b1010111 C
b10000 7
b10000 H
b1111 5
b1111 E
b110 6
b110 G
b101 4
b101 D
b1100 /
b1100 ?
b1011 <
b1011 K
08
#9
b1000 W
19
#10
09
18
#11
b1000 V
b111 U
b1000 W
19
#12
0"
b0 ;
b0 J
b0 >
0:
08
#14
b1 ;
b1 J
b1 >
#16
b10 ;
b10 J
b10 >
#18
b11 ;
b11 J
b11 >
#20
b100 ;
b100 J
b100 >
#22
b101 ;
b101 J
b101 >
#24
b1111 &
b1111 N
b10000 $
b10000 M
b1010111 '
b1010111 O
b1011 !
b1011 L
b1100 .
b1100 @
b101 %
b101 F
b110 #
b110 I
1"
b110 ;
b110 J
b110 >
#26
b101 &
b101 N
b110 $
b110 M
b1001101 '
b1001101 O
b1 !
b1 L
b10 .
b10 @
b11 %
b11 F
b100 #
b100 I
b111 ;
b111 J
b111 >
#28
09
1:
b1000 >
#29
b1000 W
19
#30
bx &
bx N
bx $
bx M
bx '
bx O
bx !
bx L
bx .
bx @
bx %
bx F
bx #
bx I
0"
b0 ;
b0 J
b0 >
0:
#32
b1 ;
b1 J
b1 >
#34
b10 ;
b10 J
b10 >
#36
b11 ;
b11 J
b11 >
#38
b100 ;
b100 J
b100 >
#40
b101 ;
b101 J
b101 >
#42
b1111 &
b1111 N
b10000 $
b10000 M
b1010111 '
b1010111 O
b1011 !
b1011 L
b1100 .
b1100 @
b101 %
b101 F
b110 #
b110 I
1"
b110 ;
b110 J
b110 >
#44
b101 &
b101 N
b110 $
b110 M
b1001101 '
b1001101 O
b1 !
b1 L
b10 .
b10 @
b11 %
b11 F
b100 #
b100 I
b111 ;
b111 J
b111 >
#46
09
12
1:
b1000 >
#47
b1000 W
b1000 X
19
#48
bx &
bx N
bx $
bx M
bx '
bx O
bx !
bx L
bx .
bx @
bx %
bx F
bx #
bx I
0"
b0 ;
b0 J
b0 >
0:
#50
b1 ;
b1 J
b1 >
#52
b10 ;
b10 J
b10 >
#54
b11 ;
b11 J
b11 >
#56
b100 ;
b100 J
b100 >
#58
b101 ;
b101 J
b101 >
#60
b1111 &
b1111 N
b10000 $
b10000 M
b1010111 '
b1010111 O
b1011 !
b1011 L
b1100 .
b1100 @
b101 %
b101 F
b110 #
b110 I
1"
b110 ;
b110 J
b110 >
#62
b101 &
b101 N
b110 $
b110 M
b1001101 '
b1001101 O
b1 !
b1 L
b10 .
b10 @
b11 %
b11 F
b100 #
b100 I
b111 ;
b111 J
b111 >
#64
09
b1111011 1
b1111011 B
b101 0
b101 A
1:
b1000 >
#65
b1000 X
b1000 W
19
#66
09
02
b111001000 1
b111001000 B
b110 0
b110 A
#67
b1000 W
19
#68
bx &
bx N
bx $
bx M
bx '
bx O
bx !
bx L
bx .
bx @
bx %
bx F
bx #
bx I
0"
b0 ;
b0 J
b0 >
0:
#70
b1 ;
b1 J
b1 >
#72
b10 ;
b10 J
b10 >
#74
b11 ;
b11 J
b11 >
#76
b100 ;
b100 J
b100 >
#78
b101 ;
b101 J
b101 >
#80
b1111011 &
b1111011 N
b111001000 $
b111001000 M
b1010111 '
b1010111 O
b1011 !
b1011 L
b1100 .
b1100 @
b0 %
b0 F
b0 #
b0 I
1"
b110 ;
b110 J
b110 >
#82
b101 &
b101 N
b110 $
b110 M
b1001101 '
b1001101 O
b1 !
b1 L
b10 .
b10 @
b11 %
b11 F
b100 #
b100 I
b111 ;
b111 J
b111 >
#84
09
12
1:
b1000 >
#85
b1010111 +
b1010111 Q
b111001000 (
b111001000 T
b1111011 )
b1111011 S
b1100 ,
b1100 P
b111 *
b111 R
b1000 X
b1000 W
19
#86
bx &
bx N
bx $
bx M
bx '
bx O
bx !
bx L
bx .
bx @
bx %
bx F
bx #
bx I
0"
b0 ;
b0 J
b0 >
0:
#88
b1 ;
b1 J
b1 >
#90
b10 ;
b10 J
b10 >
#92
b11 ;
b11 J
b11 >
#94
b100 ;
b100 J
b100 >
#96
b101 ;
b101 J
b101 >
#98
b1111011 &
b1111011 N
b111001000 $
b111001000 M
b1010111 '
b1010111 O
b1011 !
b1011 L
b1100 .
b1100 @
b0 %
b0 F
b0 #
b0 I
1"
b110 ;
b110 J
b110 >
#100
b101 &
b101 N
b110 $
b110 M
b1001101 '
b1001101 O
b1 !
b1 L
b10 .
b10 @
b11 %
b11 F
b100 #
b100 I
b111 ;
b111 J
b111 >
#102
09
b1100010101 1
b1100010101 B
b11 0
b11 A
02
1:
b1000 >
#103
b1100010101 &
b1100010101 N
b0 %
b0 F
b1000 W
19
#104
bx &
bx N
bx $
bx M
bx '
bx O
bx !
bx L
bx .
bx @
bx %
bx F
bx #
bx I
0"
b0 ;
b0 J
b0 >
0:
#106
b1 ;
b1 J
b1 >
#108
b10 ;
b10 J
b10 >
#110
b11 ;
b11 J
b11 >
#112
b100 ;
b100 J
b100 >
#114
b101 ;
b101 J
b101 >
#116
b1111011 &
b1111011 N
b111001000 $
b111001000 M
b1010111 '
b1010111 O
b1011 !
b1011 L
b1100 .
b1100 @
b0 %
b0 F
b0 #
b0 I
1"
b110 ;
b110 J
b110 >
#118
b1100010101 &
b1100010101 N
b110 $
b110 M
b1001101 '
b1001101 O
b1 !
b1 L
b10 .
b10 @
b100 #
b100 I
b111 ;
b111 J
b111 >
#120
09
b1111100111 1
b1111100111 B
b100 0
b100 A
1:
b1000 >
#121
b1111100111 $
b1111100111 M
b0 #
b0 I
b1000 W
19
#122
bx &
bx N
bx $
bx M
bx '
bx O
bx !
bx L
bx .
bx @
bx %
bx F
bx #
bx I
0"
b0 ;
b0 J
b0 >
0:
#124
b1 ;
b1 J
b1 >
#126
b10 ;
b10 J
b10 >
#128
b11 ;
b11 J
b11 >
#130
b100 ;
b100 J
b100 >
#132
b101 ;
b101 J
b101 >
#134
b1111011 &
b1111011 N
b111001000 $
b111001000 M
b1010111 '
b1010111 O
b1011 !
b1011 L
b1100 .
b1100 @
b0 %
b0 F
b0 #
b0 I
1"
b110 ;
b110 J
b110 >
#136
b1100010101 &
b1100010101 N
b1111100111 $
b1111100111 M
b1001101 '
b1001101 O
b1 !
b1 L
b10 .
b10 @
b111 ;
b111 J
b111 >
#138
09
12
1:
b1000 >
#139
b1000 W
b1001101 +
b1001101 Q
b1111100111 (
b1111100111 T
b1100010101 )
b1100010101 S
b10 ,
b10 P
b1000 *
b1000 R
b1000 X
19
#140
bx &
bx N
bx $
bx M
bx '
bx O
bx !
bx L
bx .
bx @
bx %
bx F
bx #
bx I
0"
b0 ;
b0 J
b0 >
0:
#142
b1 ;
b1 J
b1 >
#144
b10 ;
b10 J
b10 >
#146
b11 ;
b11 J
b11 >
#148
b100 ;
b100 J
b100 >
#150
b101 ;
b101 J
b101 >
#152
b1111011 &
b1111011 N
b111001000 $
b111001000 M
b1010111 '
b1010111 O
b1011 !
b1011 L
b1100 .
b1100 @
b0 %
b0 F
b0 #
b0 I
b110 ;
b110 J
b110 >
#154
b1100010101 &
b1100010101 N
b1111100111 $
b1111100111 M
b1001101 '
b1001101 O
b1 !
b1 L
b10 .
b10 @
1"
b111 ;
b111 J
b111 >
#156
09
02
1:
b1000 >
#157
b1000 W
19
#158
bx &
bx N
bx $
bx M
bx '
bx O
bx !
bx L
bx .
bx @
bx %
bx F
bx #
bx I
0"
b0 ;
b0 J
b0 >
0:
#160
b1 ;
b1 J
b1 >
#162
b10 ;
b10 J
b10 >
#164
b11 ;
b11 J
b11 >
#166
b100 ;
b100 J
b100 >
#168
b101 ;
b101 J
b101 >
#170
b1111011 &
b1111011 N
b111001000 $
b111001000 M
b1010111 '
b1010111 O
b1011 !
b1011 L
b1100 .
b1100 @
b0 %
b0 F
b0 #
b0 I
b110 ;
b110 J
b110 >
#172
b1100010101 &
b1100010101 N
b1111100111 $
b1111100111 M
b1001101 '
b1001101 O
b1 !
b1 L
b10 .
b10 @
1"
b111 ;
b111 J
b111 >
#174
09
b0 6
b0 G
b0 4
b0 D
b1101111000 <
b1101111000 K
1:
b1000 >
#175
b1000 W
19
#176
bx &
bx N
bx $
bx M
bx '
bx O
bx !
bx L
bx .
bx @
bx %
bx F
bx #
bx I
0"
b0 ;
b0 J
b0 >
0:
#178
b1 ;
b1 J
b1 >
#180
b10 ;
b10 J
b10 >
#182
b11 ;
b11 J
b11 >
#184
b100 ;
b100 J
b100 >
#186
b101 ;
b101 J
b101 >
#188
b1111011 &
b1111011 N
b111001000 $
b111001000 M
b1010111 '
b1010111 O
b1011 !
b1011 L
b1100 .
b1100 @
b0 %
b0 F
b0 #
b0 I
b110 ;
b110 J
b110 >
#190
b1100010101 &
b1100010101 N
b1111100111 $
b1111100111 M
b1001101 '
b1001101 O
b1 !
b1 L
b10 .
b10 @
1"
b111 ;
b111 J
b111 >
#192
09
18
1:
b1000 >
#193
b1000 W
b1000 V
b111 U
19
#194
bx &
bx N
bx $
bx M
bx '
bx O
bx !
bx L
bx .
bx @
bx %
bx F
bx #
bx I
0"
b0 ;
b0 J
b0 >
0:
08
#196
b1 ;
b1 J
b1 >
#198
b10 ;
b10 J
b10 >
#200
b11 ;
b11 J
b11 >
#202
b100 ;
b100 J
b100 >
#204
b101 ;
b101 J
b101 >
#206
b1111 &
b1111 N
b10000 $
b10000 M
b1010111 '
b1010111 O
b1101111000 !
b1101111000 L
b1100 .
b1100 @
b0 %
b0 F
b0 #
b0 I
1"
b110 ;
b110 J
b110 >
#208
b1100010101 &
b1100010101 N
b1111100111 $
b1111100111 M
b1001101 '
b1001101 O
b1 !
b1 L
b10 .
b10 @
b111 ;
b111 J
b111 >
#210
09
0"
12
1:
b1000 >
#211
b1000 W
b1010111 +
b1010111 Q
b10000 (
b10000 T
b1111 )
b1111 S
b1100 ,
b1100 P
b111 *
b111 R
b1000 X
19
#212
bx &
bx N
bx $
bx M
bx '
bx O
bx !
bx L
bx .
bx @
bx %
bx F
bx #
bx I
b0 ;
b0 J
b0 >
0:
#214
b1 ;
b1 J
b1 >
#216
b10 ;
b10 J
b10 >
#218
b11 ;
b11 J
b11 >
#220
b100 ;
b100 J
b100 >
#222
b101 ;
b101 J
b101 >
#224
b1111 &
b1111 N
b10000 $
b10000 M
b1010111 '
b1010111 O
b1101111000 !
b1101111000 L
b1100 .
b1100 @
b0 %
b0 F
b0 #
b0 I
1"
b110 ;
b110 J
b110 >
#226
b1100010101 &
b1100010101 N
b1111100111 $
b1111100111 M
b1001101 '
b1001101 O
b1 !
b1 L
b10 .
b10 @
0"
b111 ;
b111 J
b111 >
#228
09
1:
b1000 >
