SSOOO/Reservation Station/RS.v
module RS
(
    input clk, rst,
    input [11:0] opcode,
    input [3:0] ALUOP, 
    input [4:0] ROBEN1, ROBEN2,
    input [31:0] ROBEN1_VAL, ROBEN2_VAL,
    input [31:0] Immediate,

    input [4:0] CDB_ROBEN,
    input [31:0] CDB_ROBEN_VAL,

    input VALID_Inst,
    input FU_Is_Free,
    output FULL_FLAG,

    output reg [4:0] FU_RS_ID,
    output reg [3:0] FU_ALUOP,
    output reg [31:0] FU_Val1, FU_Val2,
    output reg [31:0] FU_Immediate



    ,input [4:0] input_index_test,
    output [11:0] opcode_test,
    output [3:0] ALUOP_test, 
    output [4:0] ROBEN1_test, ROBEN2_test,
    output [31:0] ROBEN1_VAL_test, ROBEN2_VAL_test,
    output [31:0] Immediate_test,
    output [0:0] busy_test

);


`define I(i) i[3:0]

// the ROBEN of a an instruction is the index of that instruction in the buffer plus one to avoid ROBEN value of zero
// RS buffers to store an instruction
reg [11:0] Reg_opcode [15:0];
reg [3:0] Reg_ALUOP [15:0];
reg [4:0] Reg_ROBEN1 [15:0];
reg [4:0] Reg_ROBEN2 [15:0];
reg [31:0] Reg_ROBEN1_VAL [15:0];
reg [31:0] Reg_ROBEN2_VAL [15:0];
reg [31:0] Reg_Immediate [15:0];
reg Reg_Busy [15:0];


assign opcode_test = Reg_opcode[`I(input_index_test)];
assign ALUOP_test = Reg_ALUOP[`I(input_index_test)]; 
assign ROBEN1_test = Reg_ROBEN1[`I(input_index_test)]; 
assign ROBEN2_test = Reg_ROBEN2[`I(input_index_test)];
assign ROBEN1_VAL_test = Reg_ROBEN1_VAL[`I(input_index_test)]; 
assign ROBEN2_VAL_test = Reg_ROBEN2_VAL[`I(input_index_test)];
assign Immediate_test = Reg_Immediate[`I(input_index_test)];
assign busy_test = Reg_Busy[`I(input_index_test)];

/*
this block is does the following:
    - resetting the Busy buffer to start with a clean RS
    - and if there is a new instruction is coming it enters it in the Next_Free index if there is and raise the full flag if there is no Next_Free index
*/
reg [4:0] i = 0;
reg [4:0] Next_Free = 0;
assign FULL_FLAG = ~(rst | 
                    ~(
                        Reg_Busy[0] & 
                        Reg_Busy[1] & 
                        Reg_Busy[2] & 
                        Reg_Busy[3] & 
                        Reg_Busy[4] & 
                        Reg_Busy[5] & 
                        Reg_Busy[6] & 
                        Reg_Busy[7] & 
                        Reg_Busy[8] & 
                        Reg_Busy[9] & 
                        Reg_Busy[10] & 
                        Reg_Busy[11] & 
                        Reg_Busy[12] & 
                        Reg_Busy[13] & 
                        Reg_Busy[14] & 
                        Reg_Busy[15]
                    ));
always@(posedge clk, posedge rst) begin

    if (rst) begin
        for (i = 0; i < 16; i = i + 1)
            Reg_Busy[i] = 0;
        i = 0;
        Next_Free = 0;
    end
    else if (VALID_Inst && ~FULL_FLAG) begin
        Next_Free = 0;
        for (i = 0; i < 16; i = i + 1)
            if (~Reg_Busy[`I(i)])
                Next_Free = i + 1'b1;
        if (Next_Free != 0) begin
            // the new index to use to reserve for the instruction is (Next_Free - 1)
            Reg_Busy[`I(Next_Free) - 1'b1] = 1'b1;
            Reg_opcode[`I(Next_Free) - 1'b1] = opcode;
            Reg_ALUOP[`I(Next_Free) - 1'b1] = ALUOP;
            Reg_ROBEN1 [`I(Next_Free) - 1'b1] = ROBEN1;
            Reg_ROBEN2 [`I(Next_Free) - 1'b1] = ROBEN2;
            Reg_ROBEN1_VAL [`I(Next_Free) - 1'b1] = ROBEN1_VAL;
            Reg_ROBEN2_VAL [`I(Next_Free) - 1'b1] = ROBEN2_VAL;
            Reg_Immediate [`I(Next_Free) - 1'b1] = Immediate;
        end
    end
end

/*
this block does the following:
    - monitors the CDB to see if there is a match with RS ID that they are waiting for and take their value to be ready
*/
reg [4:0] j;
always@(posedge clk, posedge rst) begin
    for (j = 0; j < 16; j = j + 1) begin
        if (Reg_Busy[`I(j)]) begin
            if (Reg_ROBEN1[`I(j)] == CDB_ROBEN) begin
                Reg_ROBEN1_VAL[`I(j)] = CDB_ROBEN_VAL;
                Reg_ROBEN1[`I(j)] = 0;
            end
            if (Reg_ROBEN2[`I(j)] == CDB_ROBEN) begin
                Reg_ROBEN2_VAL[`I(j)] = CDB_ROBEN_VAL;
                Reg_ROBEN2[`I(j)] = 0;
            end
        end
    end
end



/*
this block does the following:
    - if the FU is free it picks a ready instruction to execute it and once finish it releases the reserved entry by resetting the busy bit
*/
reg [4:0] k;
always@(posedge clk, posedge rst) begin
    if (rst) begin
        FU_RS_ID = 0;
    end
    else if (FU_Is_Free) begin
        for (k = 0; k < 16; k = k + 1) begin
            // TODO: modify on the way of picking the ready instruction
            // (it is ok for now because of the small size of the station)
            if (Reg_Busy[`I(k)] && Reg_ROBEN1[`I(k)] == 0 && Reg_ROBEN2[`I(k)] == 0) begin
                FU_RS_ID = k + 1'b1;
                FU_ALUOP = Reg_ALUOP[`I(k)];
                FU_Val1 = Reg_ROBEN1_VAL[`I(k)];
                FU_Val2 = Reg_ROBEN2_VAL[`I(k)];
                FU_Immediate = Reg_Immediate[`I(k)];
            end
        end
    end
end

always@(posedge FU_Is_Free) begin
    if (FU_RS_ID != 0)
        Reg_Busy[`I(FU_RS_ID) - 1'b1] = 1'b0;
end



endmodule

SSOOO/Reservation Station/RS_tb.v

`define HALF_CYCLE 1
`define ONE_CLK (2 * `HALF_CYCLE)
`define ADVANCE_N_CYCLE(N) #(`ONE_CLK * N);

`define DISPLAYVALS \
$display("full = %b , valid = %b", FULL_FLAG, VALID_Inst); \
clk_en = 0; \
for (i = 0; i < 16; i = i + 1) begin \
    input_index_test = i[4:0]; \
    #`ONE_CLK $display("index %d: busy = %b , opcode = %d , ALUOP = %d , ROBEN1 = %d , ROBEN1_VAL = %d , ROBEN2 = %d , ROBEN2_VAL = %d , Immediate = %d", \
    input_index_test, busy_test, opcode_test, ALUOP_test, ROBEN1_test, ROBEN1_VAL_test, ROBEN2_test, ROBEN2_VAL_test, Immediate_test); \
end \
$display("FU_Is_Free = %b", FU_Is_Free); \
$display("FU_RS_ID = %d , FU_ALUOP = %d , FU_VAL1 = %d , FU_VAL2 = %d , FU_Immediate = %d\n", FU_RS_ID, FU_ALUOP, FU_Val1, FU_Val2, FU_Immediate); \
clk_en = 1;



`include "RS.v"

module RS_tb();


reg clk = 0, rst;
reg [11:0] opcode;
reg [3:0] ALUOP;
reg [4:0] ROBEN1, ROBEN2;
reg [31:0] ROBEN1_VAL, ROBEN2_VAL;
reg [31:0] Immediate;
reg [4:0] CDB_ROBEN;
reg [31:0] CDB_ROBEN_VAL;

reg VALID_Inst;
reg FU_Is_Free;

wire FULL_FLAG;
wire [4:0] FU_RS_ID;
wire [3:0] FU_ALUOP;
wire [31:0] FU_Val1, FU_Val2;
wire [31:0] FU_Immediate;


reg  [4:0] input_index_test;
wire [11:0] opcode_test;
wire [3:0] ALUOP_test;
wire [4:0] ROBEN1_test, ROBEN2_test;
wire [31:0] ROBEN1_VAL_test, ROBEN2_VAL_test;
wire [31:0] Immediate_test;
wire busy_test;

RS dut
(
    .clk(clk), 
    .rst(rst),
    .opcode(opcode),
    .ALUOP(ALUOP), 
    .ROBEN1(ROBEN1), 
    .ROBEN2(ROBEN2),
    .ROBEN1_VAL(ROBEN1_VAL), 
    .ROBEN2_VAL(ROBEN2_VAL),
    .Immediate(Immediate),
    .CDB_ROBEN(CDB_ROBEN),
    .CDB_ROBEN_VAL(CDB_ROBEN_VAL),
    .VALID_Inst(VALID_Inst),
    .FU_Is_Free(FU_Is_Free),
    .FULL_FLAG(FULL_FLAG),
    .FU_RS_ID(FU_RS_ID),
    .FU_ALUOP(FU_ALUOP),
    .FU_Val1(FU_Val1), 
    .FU_Val2(FU_Val2),
    .FU_Immediate(FU_Immediate),

    .input_index_test(input_index_test),
    .opcode_test(opcode_test),
    .ALUOP_test(ALUOP_test), 
    .ROBEN1_test(ROBEN1_test), 
    .ROBEN2_test(ROBEN2_test),
    .ROBEN1_VAL_test(ROBEN1_VAL_test), 
    .ROBEN2_VAL_test(ROBEN2_VAL_test),
    .Immediate_test(Immediate_test),
    .busy_test(busy_test)

);


reg clk_en = 0;
always begin
        #(`HALF_CYCLE) clk <= (~clk_en & clk) | (clk_en & ~clk);
end

integer i;
initial begin
$dumpfile("testout.vcd");
$dumpvars;
clk_en = 1;
FU_Is_Free = 0;
rst = 0; `ADVANCE_N_CYCLE(1); rst = 1; `ADVANCE_N_CYCLE(1); rst = 0;


opcode = 1;
ALUOP = 2;
ROBEN1 = 3;
ROBEN2 = 4;
ROBEN1_VAL = 5;
ROBEN2_VAL = 6;
Immediate = 77;
// adding an invalid instruction
VALID_Inst = 0;
`ADVANCE_N_CYCLE(1);
// `DISPLAYVALS
// adding a valid instruction
VALID_Inst = 1;
`ADVANCE_N_CYCLE(1);
VALID_Inst = 0;
// `DISPLAYVALS
opcode = 1 + 10;
ALUOP = 2 + 10;
ROBEN1 = 3 + 2;
ROBEN2 = 4 + 2;
ROBEN1_VAL = 5 + 10;
ROBEN2_VAL = 6 + 10;
Immediate = 77 + 10;
`ADVANCE_N_CYCLE(1);
// `DISPLAYVALS
// adding another instruction
VALID_Inst = 1;
`ADVANCE_N_CYCLE(1);
VALID_Inst = 0;
// `DISPLAYVALS

// // this is for testing the full flag, and it works
// opcode = 888;
// VALID_Inst = 1;
// `ADVANCE_N_CYCLE(14);
// VALID_Inst = 0;
// `DISPLAYVALS
// opcode = 999;
// VALID_Inst = 1;
// `ADVANCE_N_CYCLE(1);
// VALID_Inst = 0;
// `DISPLAYVALS
// $finish;

// here we have two instructions waiting for there operands
FU_Is_Free = 0;
`ADVANCE_N_CYCLE(1);
`DISPLAYVALS

FU_Is_Free = 1;
`ADVANCE_N_CYCLE(1);
`DISPLAYVALS

CDB_ROBEN = 5;
CDB_ROBEN_VAL = 123;
`ADVANCE_N_CYCLE(1);
CDB_ROBEN = 6;
CDB_ROBEN_VAL = 456;

FU_Is_Free = 0;
`ADVANCE_N_CYCLE(1);
`DISPLAYVALS

FU_Is_Free = 1;
`ADVANCE_N_CYCLE(1);
`DISPLAYVALS


FU_Is_Free = 0;
CDB_ROBEN = 3;
CDB_ROBEN_VAL = 789;
`ADVANCE_N_CYCLE(1);
`DISPLAYVALS

CDB_ROBEN = 4;
CDB_ROBEN_VAL = 999;
`ADVANCE_N_CYCLE(1);
`DISPLAYVALS


FU_Is_Free = 1;
`ADVANCE_N_CYCLE(1);
`DISPLAYVALS

FU_Is_Free = 0;
`ADVANCE_N_CYCLE(1);
`DISPLAYVALS

$display("Now we want to enter a new instruction after executing it---------------------------------------------------------------------");
opcode = 888;
ROBEN1 = 0;
ROBEN2 = 0;
`ADVANCE_N_CYCLE(1);
`DISPLAYVALS

VALID_Inst = 1;
`ADVANCE_N_CYCLE(1);
VALID_Inst = 0;
`DISPLAYVALS

FU_Is_Free = 1;
`ADVANCE_N_CYCLE(1);
`DISPLAYVALS


$finish;
end




endmodule

SSOOO/Reservation Station/testout.vcd
$date
	Wed Dec 25 18:40:33 2024
$end
$version
	Icarus Verilog
$end
$timescale
	1s
$end
$scope module RS_tb $end
$var wire 12 ! opcode_test [11:0] $end
$var wire 1 " busy_test $end
$var wire 5 # ROBEN2_test [4:0] $end
$var wire 32 $ ROBEN2_VAL_test [31:0] $end
$var wire 5 % ROBEN1_test [4:0] $end
$var wire 32 & ROBEN1_VAL_test [31:0] $end
$var wire 32 ' Immediate_test [31:0] $end
$var wire 32 ( FU_Val2 [31:0] $end
$var wire 32 ) FU_Val1 [31:0] $end
$var wire 5 * FU_RS_ID [4:0] $end
$var wire 32 + FU_Immediate [31:0] $end
$var wire 4 , FU_ALUOP [3:0] $end
$var wire 1 - FULL_FLAG $end
$var wire 4 . ALUOP_test [3:0] $end
$var reg 4 / ALUOP [3:0] $end
$var reg 5 0 CDB_ROBEN [4:0] $end
$var reg 32 1 CDB_ROBEN_VAL [31:0] $end
$var reg 1 2 FU_Is_Free $end
$var reg 32 3 Immediate [31:0] $end
$var reg 5 4 ROBEN1 [4:0] $end
$var reg 32 5 ROBEN1_VAL [31:0] $end
$var reg 5 6 ROBEN2 [4:0] $end
$var reg 32 7 ROBEN2_VAL [31:0] $end
$var reg 1 8 VALID_Inst $end
$var reg 1 9 clk $end
$var reg 1 : clk_en $end
$var reg 5 ; input_index_test [4:0] $end
$var reg 12 < opcode [11:0] $end
$var reg 1 = rst $end
$var integer 32 > i [31:0] $end
$scope module dut $end
$var wire 4 ? ALUOP [3:0] $end
$var wire 4 @ ALUOP_test [3:0] $end
$var wire 5 A CDB_ROBEN [4:0] $end
$var wire 32 B CDB_ROBEN_VAL [31:0] $end
$var wire 1 - FULL_FLAG $end
$var wire 1 2 FU_Is_Free $end
$var wire 32 C Immediate [31:0] $end
$var wire 32 D Immediate_test [31:0] $end
$var wire 5 E ROBEN1 [4:0] $end
$var wire 32 F ROBEN1_VAL [31:0] $end
$var wire 32 G ROBEN1_VAL_test [31:0] $end
$var wire 5 H ROBEN1_test [4:0] $end
$var wire 5 I ROBEN2 [4:0] $end
$var wire 32 J ROBEN2_VAL [31:0] $end
$var wire 32 K ROBEN2_VAL_test [31:0] $end
$var wire 5 L ROBEN2_test [4:0] $end
$var wire 1 8 VALID_Inst $end
$var wire 1 " busy_test $end
$var wire 1 9 clk $end
$var wire 5 M input_index_test [4:0] $end
$var wire 12 N opcode [11:0] $end
$var wire 12 O opcode_test [11:0] $end
$var wire 1 = rst $end
$var reg 4 P FU_ALUOP [3:0] $end
$var reg 32 Q FU_Immediate [31:0] $end
$var reg 5 R FU_RS_ID [4:0] $end
$var reg 32 S FU_Val1 [31:0] $end
$var reg 32 T FU_Val2 [31:0] $end
$var reg 5 U Next_Free [4:0] $end
$var reg 5 V i [4:0] $end
$var reg 5 W j [4:0] $end
$var reg 5 X k [4:0] $end
$upscope $end
$upscope $end
$enddefinitions $end
$comment Show the parameter values. $end
$dumpall
$end
#0
$dumpvars
bx X
bx W
b0 V
b0 U
bx T
bx S
bx R
bx Q
bx P
bx O
bx N
bx M
bx L
bx K
bx J
bx I
bx H
bx G
bx F
bx E
bx D
bx C
bx B
bx A
bx @
bx ?
bx >
0=
bx <
bx ;
1:
09
x8
bx 7
bx 6
bx 5
bx 4
bx 3
02
bx 1
bx 0
bx /
bx .
x-
bx ,
bx +
bx *
bx )
bx (
bx '
bx &
bx %
bx $
bx #
x"
bx !
$end
#1
b10000 W
19
#2
09
0-
b0 *
b0 R
b10000 W
b0 V
1=
#3
b0 V
b10000 W
19
#4
09
08
b1001101 3
b1001101 C
b110 7
b110 J
b101 5
b101 F
b100 6
b100 I
b11 4
b11 E
b10 /
b10 ?
b1 <
b1 N
0=
#5
b10000 W
19
#6
0"
b0 ;
b0 M
b0 >
0:
#8
b1 ;
b1 M
b1 >
#10
b10 ;
b10 M
b10 >
#12
b11 ;
b11 M
b11 >
#14
b100 ;
b100 M
b100 >
#16
b101 ;
b101 M
b101 >
#18
b110 ;
b110 M
b110 >
#20
b111 ;
b111 M
b111 >
#22
b1000 ;
b1000 M
b1000 >
#24
b1001 ;
b1001 M
b1001 >
#26
b1010 ;
b1010 M
b1010 >
#28
b1011 ;
b1011 M
b1011 >
#30
b1100 ;
b1100 M
b1100 >
#32
b1101 ;
b1101 M
b1101 >
#34
b1110 ;
b1110 M
b1110 >
#36
b1111 ;
b1111 M
b1111 >
#38
09
18
1:
b10000 >
#39
b1001101 '
b1001101 D
b110 $
b110 K
b101 &
b101 G
b100 #
b100 L
b11 %
b11 H
b10 .
b10 @
b1 !
b1 O
1"
b10000 V
b10000 U
b10000 W
19
#40
bx !
bx O
bx .
bx @
bx %
bx H
bx #
bx L
bx &
bx G
bx $
bx K
bx '
bx D
0"
b0 ;
b0 M
b0 >
0:
08
#42
b1 ;
b1 M
b1 >
#44
b10 ;
b10 M
b10 >
#46
b11 ;
b11 M
b11 >
#48
b100 ;
b100 M
b100 >
#50
b101 ;
b101 M
b101 >
#52
b110 ;
b110 M
b110 >
#54
b111 ;
b111 M
b111 >
#56
b1000 ;
b1000 M
b1000 >
#58
b1001 ;
b1001 M
b1001 >
#60
b1010 ;
b1010 M
b1010 >
#62
b1011 ;
b1011 M
b1011 >
#64
b1100 ;
b1100 M
b1100 >
#66
b1101 ;
b1101 M
b1101 >
#68
b1110 ;
b1110 M
b1110 >
#70
b1 !
b1 O
b10 .
b10 @
b11 %
b11 H
b100 #
b100 L
b101 &
b101 G
b110 $
b110 K
b1001101 '
b1001101 D
1"
b1111 ;
b1111 M
b1111 >
#72
09
b1010111 3
b1010111 C
b10000 7
b10000 J
b1111 5
b1111 F
b110 6
b110 I
b101 4
b101 E
b1100 /
b1100 ?
b1011 <
b1011 N
1:
b10000 >
#73
b10000 W
19
#74
bx !
bx O
bx .
bx @
bx %
bx H
bx #
bx L
bx &
bx G
bx $
bx K
bx '
bx D
0"
b0 ;
b0 M
b0 >
0:
#76
b1 ;
b1 M
b1 >
#78
b10 ;
b10 M
b10 >
#80
b11 ;
b11 M
b11 >
#82
b100 ;
b100 M
b100 >
#84
b101 ;
b101 M
b101 >
#86
b110 ;
b110 M
b110 >
#88
b111 ;
b111 M
b111 >
#90
b1000 ;
b1000 M
b1000 >
#92
b1001 ;
b1001 M
b1001 >
#94
b1010 ;
b1010 M
b1010 >
#96
b1011 ;
b1011 M
b1011 >
#98
b1100 ;
b1100 M
b1100 >
#100
b1101 ;
b1101 M
b1101 >
#102
b1110 ;
b1110 M
b1110 >
#104
b1 !
b1 O
b10 .
b10 @
b11 %
b11 H
b100 #
b100 L
b101 &
b101 G
b110 $
b110 K
b1001101 '
b1001101 D
1"
b1111 ;
b1111 M
b1111 >
#106
09
18
1:
b10000 >
#107
b10000 V
b1111 U
b10000 W
19
#108
bx !
bx O
bx .
bx @
bx %
bx H
bx #
bx L
bx &
bx G
bx $
bx K
bx '
bx D
0"
b0 ;
b0 M
b0 >
0:
08
#110
b1 ;
b1 M
b1 >
#112
b10 ;
b10 M
b10 >
#114
b11 ;
b11 M
b11 >
#116
b100 ;
b100 M
b100 >
#118
b101 ;
b101 M
b101 >
#120
b110 ;
b110 M
b110 >
#122
b111 ;
b111 M
b111 >
#124
b1000 ;
b1000 M
b1000 >
#126
b1001 ;
b1001 M
b1001 >
#128
b1010 ;
b1010 M
b1010 >
#130
b1011 ;
b1011 M
b1011 >
#132
b1100 ;
b1100 M
b1100 >
#134
b1101 ;
b1101 M
b1101 >
#136
b1011 !
b1011 O
b1100 .
b1100 @
b101 %
b101 H
b110 #
b110 L
b1111 &
b1111 G
b10000 $
b10000 K
b1010111 '
b1010111 D
1"
b1110 ;
b1110 M
b1110 >
#138
b1 !
b1 O
b10 .
b10 @
b11 %
b11 H
b100 #
b100 L
b101 &
b101 G
b110 $
b110 K
b1001101 '
b1001101 D
b1111 ;
b1111 M
b1111 >
#140
09
18
b1101111000 <
b1101111000 N
1:
b10000 >
#141
b10000 W
b10000 V
b1110 U
19
#142
09
#143
b10000 V
b1101 U
b10000 W
19
#144
09
#145
b10000 W
b10000 V
b1100 U
19
#146
09
#147
b10000 V
b1011 U
b10000 W
19
#148
09
#149
b10000 W
b10000 V
b1010 U
19
#150
09
#151
b10000 V
b1001 U
b10000 W
19
#152
09
#153
b10000 W
b10000 V
b1000 U
19
#154
09
#155
b10000 V
b111 U
b10000 W
19
#156
09
#157
b10000 W
b10000 V
b110 U
19
#158
09
#159
b10000 V
b101 U
b10000 W
19
#160
09
#161
b10000 W
b10000 V
b100 U
19
#162
09
#163
b10000 V
b11 U
b10000 W
19
#164
09
#165
b10000 W
b10000 V
b10 U
19
#166
09
#167
1-
b10000 V
b1 U
b10000 W
19
#168
b1101111000 !
b1101111000 O
b1100 .
b1100 @
b101 %
b101 H
b110 #
b110 L
b1111 &
b1111 G
b10000 $
b10000 K
b1010111 '
b1010111 D
b0 ;
b0 M
b0 >
0:
08
#170
b1 ;
b1 M
b1 >
#172
b10 ;
b10 M
b10 >
#174
b11 ;
b11 M
b11 >
#176
b100 ;
b100 M
b100 >
#178
b101 ;
b101 M
b101 >
#180
b110 ;
b110 M
b110 >
#182
b111 ;
b111 M
b111 >
#184
b1000 ;
b1000 M
b1000 >
#186
b1001 ;
b1001 M
b1001 >
#188
b1010 ;
b1010 M
b1010 >
#190
b1011 ;
b1011 M
b1011 >
#192
b1100 ;
b1100 M
b1100 >
#194
b1101 ;
b1101 M
b1101 >
#196
b1011 !
b1011 O
b1110 ;
b1110 M
b1110 >
#198
b1 !
b1 O
b10 .
b10 @
b11 %
b11 H
b100 #
b100 L
b101 &
b101 G
b110 $
b110 K
b1001101 '
b1001101 D
b1111 ;
b1111 M
b1111 >
#200
09
18
b1111100111 <
b1111100111 N
1:
b10000 >
#201
b10000 W
19
#202
b1101111000 !
b1101111000 O
b1100 .
b1100 @
b101 %
b101 H
b110 #
b110 L
b1111 &
b1111 G
b10000 $
b10000 K
b1010111 '
b1010111 D
b0 ;
b0 M
b0 >
0:
08
#204
b1 ;
b1 M
b1 >
#206
b10 ;
b10 M
b10 >
#208
b11 ;
b11 M
b11 >
#210
b100 ;
b100 M
b100 >
#212
b101 ;
b101 M
b101 >
#214
b110 ;
b110 M
b110 >
#216
b111 ;
b111 M
b111 >
#218
b1000 ;
b1000 M
b1000 >
#220
b1001 ;
b1001 M
b1001 >
#222
b1010 ;
b1010 M
b1010 >
#224
b1011 ;
b1011 M
b1011 >
#226
b1100 ;
b1100 M
b1100 >
#228
b1101 ;
b1101 M
b1101 >
#230
b1011 !
b1011 O
b1110 ;
b1110 M
b1110 >
#232
b1 !
b1 O
b10 .
b10 @
b11 %
b11 H
b100 #
b100 L
b101 &
b101 G
b110 $
b110 K
b1001101 '
b1001101 D
b1111 ;
b1111 M
b1111 >
#234
09
1:
b10000 >
