SSOOO/Reservation Station(s)/RS.v
module RS
(
    input clk, rst,
    input [11:0] opcode,
    input [3:0] ALUOP, 
    input [2:0] RS_ID1, RS_ID2,
    input [31:0] RS_ID1_VAL, RS_ID2_VAL,
    input [31:0] Immediate,

    input [2:0] CDB_RS_ID,
    input [31:0] CDB_RS_ID_VAL,

    input VALID_Inst,
    input FU_Is_Free,

    output reg FULL_FLAG,

    output reg [3:0] FU_RS_ID,
    output reg [3:0] FU_ALUOP,
    output reg [31:0] FU_Val1, FU_Val2,
    output reg [31:0] FU_Immediate,

    input [3:0] input_index_test,
    output [11:0] opcode_test,
    output [3:0] ALUOP_test, 
    output [2:0] RS_ID1_test, RS_ID2_test,
    output [31:0] RS_ID1_VAL_test, RS_ID2_VAL_test,
    output [31:0] Immediate_test,
    output [0:0] busy_test

);


`define I(i) i[2:0]

// the RS_ID of a an instruction is the index of that instruction in the buffer plus one to avoid RS_ID value of zero
// RS buffers to store an instruction
reg [11:0] Reg_opcodes [7:0];
reg [3:0] Reg_ALUOPs [7:0];
reg [2:0] Reg_RS_ID1 [7:0];
reg [2:0] Reg_RS_ID2 [7:0];
reg [32:0] Reg_RS_ID1_VAL [7:0];
reg [32:0] Reg_RS_ID2_VAL [7:0];
reg [32:0] Reg_Immediate [7:0];
reg Reg_Busy [7:0];


assign opcode_test = Reg_opcodes[`I(input_index_test)];
assign ALUOP_test = Reg_ALUOPs[`I(input_index_test)]; 
assign RS_ID1_test = Reg_RS_ID1[`I(input_index_test)]; 
assign RS_ID2_test = Reg_RS_ID2[`I(input_index_test)];
assign RS_ID1_VAL_test = Reg_RS_ID1_VAL[`I(input_index_test)]; 
assign RS_ID2_VAL_test = Reg_RS_ID2_VAL[`I(input_index_test)];
assign Immediate_test = Reg_Immediate[`I(input_index_test)];
assign busy_test = Reg_Busy[`I(input_index_test)];

/*
this block is do the following:
    - resetting the Busy buffer to start with a clean RS
    - and if there is a new instruction is coming it enters it in the Next_Free index if there is and raise the full flag if there is no Next_Free index
*/
reg [3:0] i = 0;
reg [3:0] Next_Free = 0;
always@(posedge clk, posedge rst) begin

    if (rst) begin
        for (i = 0; i < 8; i = i + 1)
            Reg_Busy[i] = 0;
        i = 0;
        Next_Free = 0;
        FULL_FLAG = 0;
    end
    else if (VALID_Inst) begin
        Next_Free = 0;
        for (i = 0; i < 8; i = i + 1)
            if (~Reg_Busy[`I(i)])
                Next_Free = i + 1'b1;
        if (Next_Free != 0) begin
            // the new index to use to reserve for the instruction is (Next_Free - 1)
            Reg_Busy[`I(Next_Free) - 1'b1] = 1'b1;
            Reg_opcodes[`I(Next_Free) - 1'b1] = opcode;
            Reg_ALUOPs[`I(Next_Free) - 1'b1] = ALUOP;
            Reg_RS_ID1 [`I(Next_Free) - 1'b1] = RS_ID1;
            Reg_RS_ID2 [`I(Next_Free) - 1'b1] = RS_ID2;
            Reg_RS_ID1_VAL [`I(Next_Free) - 1'b1] = RS_ID1_VAL;
            Reg_RS_ID2_VAL [`I(Next_Free) - 1'b1] = RS_ID2_VAL;
            Reg_Immediate [`I(Next_Free) - 1'b1] = Immediate;
            FULL_FLAG = 1'b0;
        end
        else begin
            FULL_FLAG = 1'b1;
        end
    end
end

/*
this block do the following:
    - monitors the CDB to see if there is a match with RS ID that they are waiting for and take their value to be ready
*/
reg [3:0] j;
always@(posedge clk, posedge rst) begin
    for (j = 0; j < 8; j = j + 1) begin
        if (Reg_Busy[`I(j)]) begin
            if (Reg_RS_ID1[`I(j)] == CDB_RS_ID) begin
                Reg_RS_ID1_VAL[`I(j)] = CDB_RS_ID_VAL;
                Reg_RS_ID1[`I(j)] = 0;
            end
            if (Reg_RS_ID2[`I(j)] == CDB_RS_ID) begin
                Reg_RS_ID2_VAL[`I(j)] = CDB_RS_ID_VAL;
                Reg_RS_ID2[`I(j)] = 0;
            end
        end
    end
end




reg [3:0] k;
always@(posedge clk, posedge rst) begin
    if (FU_Is_Free) begin
        for (k = 0; k < 8; k = k + 1) begin
            // TODO: modify on the way of picking the ready instruction
            if (Reg_Busy[`I(k)] && Reg_RS_ID1[`I(k)] == 0 && Reg_RS_ID2[`I(k)] == 0) begin
                FU_RS_ID = k + 1'b1;
                FU_ALUOP = Reg_ALUOPs[`I(k)];
                FU_Val1 = Reg_RS_ID1_VAL[`I(k)];
                FU_Val2 = Reg_RS_ID2_VAL[`I(k)];
                FU_Immediate = Reg_Immediate[`I(k)];
            end
        end
    end
end

always@(posedge FU_Is_Free) begin
    Reg_Busy[`I(FU_RS_ID) - 1'b1] = 1'b0;
end



endmodule

SSOOO/Reservation Station(s)/RS_tb.v

`define HALF_CYCLE 1
`define ONE_CLK (2 * `HALF_CYCLE)
`define ADVANCE_N_CYCLE(N) #(`ONE_CLK * N);

`define DISPLAYVALS \
$display("full = %b , valid = %b", FULL_FLAG, VALID_Inst); \
for (i = 0; i < 8; i = i + 1) begin \
    input_index_test = i[3:0]; \
    #`ONE_CLK $display("index %d: busy = %b , opcode = %d , ALUOP = %d , RS_ID1 = %d , RS_ID1_VAL = %d , RS_ID2 = %d , RS_ID2_VAL = %d , Immediate = %d", \
    input_index_test, busy_test, opcode_test, ALUOP_test, RS_ID1_test, RS_ID1_VAL_test, RS_ID2_test, RS_ID2_VAL_test, Immediate_test); \
end \
$display("FU_Is_Free = %b", FU_Is_Free); \
$display("FU_RS_ID = %d , FU_ALUOP = %d , FU_VAL1 = %d , FU_VAL2 = %d , FU_Immediate = %d\n", FU_RS_ID, FU_ALUOP, FU_Val1, FU_Val2, FU_Immediate);



`include "RS.v"

module RS_tb();


reg clk = 0, rst;
reg [11:0] opcode;
reg [3:0] ALUOP;
reg [2:0] RS_ID1, RS_ID2;
reg [31:0] RS_ID1_VAL, RS_ID2_VAL;
reg [31:0] Immediate;
reg [2:0] CDB_RS_ID;
reg [31:0] CDB_RS_ID_VAL;

reg VALID_Inst;
reg FU_Is_Free;

wire FULL_FLAG;
wire [3:0] FU_RS_ID;
wire [3:0] FU_ALUOP;
wire [31:0] FU_Val1, FU_Val2;
wire [31:0] FU_Immediate;


reg [3:0] input_index_test;
wire [11:0] opcode_test;
wire [3:0] ALUOP_test;
wire [2:0] RS_ID1_test, RS_ID2_test;
wire [31:0] RS_ID1_VAL_test, RS_ID2_VAL_test;
wire [31:0] Immediate_test;
wire busy_test;

RS dut
(
    .clk(clk), 
    .rst(rst),
    .opcode(opcode),
    .ALUOP(ALUOP), 
    .RS_ID1(RS_ID1), 
    .RS_ID2(RS_ID2),
    .RS_ID1_VAL(RS_ID1_VAL), 
    .RS_ID2_VAL(RS_ID2_VAL),
    .Immediate(Immediate),
    .CDB_RS_ID(CDB_RS_ID),
    .CDB_RS_ID_VAL(CDB_RS_ID_VAL),
    .VALID_Inst(VALID_Inst),
    .FU_Is_Free(FU_Is_Free),
    .FULL_FLAG(FULL_FLAG),
    .FU_RS_ID(FU_RS_ID),
    .FU_ALUOP(FU_ALUOP),
    .FU_Val1(FU_Val1), 
    .FU_Val2(FU_Val2),
    .FU_Immediate(FU_Immediate),

    .input_index_test(input_index_test),
    .opcode_test(opcode_test),
    .ALUOP_test(ALUOP_test), 
    .RS_ID1_test(RS_ID1_test), 
    .RS_ID2_test(RS_ID2_test),
    .RS_ID1_VAL_test(RS_ID1_VAL_test), 
    .RS_ID2_VAL_test(RS_ID2_VAL_test),
    .Immediate_test(Immediate_test),
    .busy_test(busy_test)

);


always #(`HALF_CYCLE) clk <= ~clk;
integer i;
initial begin
$dumpfile("testout.vcd");
$dumpvars;
FU_Is_Free = 0;
rst = 0; `ADVANCE_N_CYCLE(1); rst = 1; `ADVANCE_N_CYCLE(1); rst = 0;


opcode = 1;
ALUOP = 2;
RS_ID1 = 3;
RS_ID2 = 4;
RS_ID1_VAL = 5;
RS_ID2_VAL = 6;
Immediate = 77;
// adding an invalid instruction
VALID_Inst = 0;
`ADVANCE_N_CYCLE(1);
// `DISPLAYVALS
// adding a valid instruction
VALID_Inst = 1;
`ADVANCE_N_CYCLE(1);
VALID_Inst = 0;
// `DISPLAYVALS
opcode = 1 + 10;
ALUOP = 2 + 10;
RS_ID1 = 3 + 2;
RS_ID2 = 4 + 2;
RS_ID1_VAL = 5 + 10;
RS_ID2_VAL = 6 + 10;
Immediate = 77 + 10;
`ADVANCE_N_CYCLE(1);
// `DISPLAYVALS
// adding another instruction
VALID_Inst = 1;
`ADVANCE_N_CYCLE(1);
VALID_Inst = 0;
`DISPLAYVALS

// this is for testing the full flag, and it works
// opcode = 888;
// VALID_Inst = 1;
// `ADVANCE_N_CYCLE(6);
// VALID_Inst = 0;
// `DISPLAYVALS
// opcode = 999;
// VALID_Inst = 1;
// `ADVANCE_N_CYCLE(1);
// VALID_Inst = 0;
// `DISPLAYVALS
// $finish;

// here we have two instructions waiting for there operands
FU_Is_Free = 0;
`ADVANCE_N_CYCLE(1);
`DISPLAYVALS

FU_Is_Free = 1;
`ADVANCE_N_CYCLE(1);
`DISPLAYVALS

CDB_RS_ID = 5;
CDB_RS_ID_VAL = 123;
`ADVANCE_N_CYCLE(1);
CDB_RS_ID = 6;
CDB_RS_ID_VAL = 456;

FU_Is_Free = 0;
`ADVANCE_N_CYCLE(1);
`DISPLAYVALS

FU_Is_Free = 1;
`ADVANCE_N_CYCLE(1);
`DISPLAYVALS


FU_Is_Free = 0;
CDB_RS_ID = 3;
CDB_RS_ID_VAL = 789;
`ADVANCE_N_CYCLE(1);
`DISPLAYVALS

CDB_RS_ID = 4;
CDB_RS_ID_VAL = 999;
`ADVANCE_N_CYCLE(1);
`DISPLAYVALS


FU_Is_Free = 1;
`ADVANCE_N_CYCLE(1);
`DISPLAYVALS

FU_Is_Free = 0;
`ADVANCE_N_CYCLE(1);
`DISPLAYVALS

$display("Now we want to enter a new instruction after executing it---------------------------------------------------------------------");
opcode = 888;
RS_ID1 = 0;
RS_ID2 = 0;
`ADVANCE_N_CYCLE(1);
`DISPLAYVALS

VALID_Inst = 1;
`ADVANCE_N_CYCLE(1);
VALID_Inst = 0;
`DISPLAYVALS

FU_Is_Free = 1;
`ADVANCE_N_CYCLE(1);
`DISPLAYVALS


$finish;
end




endmodule

SSOOO/Reservation Station(s)/testout.vcd
$date
	Fri Dec 20 19:56:14 2024
$end
$version
	Icarus Verilog
$end
$timescale
	1s
$end
$scope module RS_tb $end
$var wire 12 ! opcode_test [11:0] $end
$var wire 1 " busy_test $end
$var wire 3 # RS_ID2_test [2:0] $end
$var wire 32 $ RS_ID2_VAL_test [31:0] $end
$var wire 3 % RS_ID1_test [2:0] $end
$var wire 32 & RS_ID1_VAL_test [31:0] $end
$var wire 32 ' Immediate_test [31:0] $end
$var wire 32 ( FU_Val2 [31:0] $end
$var wire 32 ) FU_Val1 [31:0] $end
$var wire 4 * FU_RS_ID [3:0] $end
$var wire 32 + FU_Immediate [31:0] $end
$var wire 4 , FU_ALUOP [3:0] $end
$var wire 1 - FULL_FLAG $end
$var wire 4 . ALUOP_test [3:0] $end
$var reg 4 / ALUOP [3:0] $end
$var reg 3 0 CDB_RS_ID [2:0] $end
$var reg 32 1 CDB_RS_ID_VAL [31:0] $end
$var reg 1 2 FU_Is_Free $end
$var reg 32 3 Immediate [31:0] $end
$var reg 3 4 RS_ID1 [2:0] $end
$var reg 32 5 RS_ID1_VAL [31:0] $end
$var reg 3 6 RS_ID2 [2:0] $end
$var reg 32 7 RS_ID2_VAL [31:0] $end
$var reg 1 8 VALID_Inst $end
$var reg 1 9 clk $end
$var reg 4 : input_index_test [3:0] $end
$var reg 12 ; opcode [11:0] $end
$var reg 1 < rst $end
$var integer 32 = i [31:0] $end
$scope module dut $end
$var wire 4 > ALUOP [3:0] $end
$var wire 4 ? ALUOP_test [3:0] $end
$var wire 3 @ CDB_RS_ID [2:0] $end
$var wire 32 A CDB_RS_ID_VAL [31:0] $end
$var wire 1 2 FU_Is_Free $end
$var wire 32 B Immediate [31:0] $end
$var wire 3 C RS_ID1 [2:0] $end
$var wire 32 D RS_ID1_VAL [31:0] $end
$var wire 3 E RS_ID1_test [2:0] $end
$var wire 3 F RS_ID2 [2:0] $end
$var wire 32 G RS_ID2_VAL [31:0] $end
$var wire 3 H RS_ID2_test [2:0] $end
$var wire 1 8 VALID_Inst $end
$var wire 1 " busy_test $end
$var wire 1 9 clk $end
$var wire 4 I input_index_test [3:0] $end
$var wire 12 J opcode [11:0] $end
$var wire 12 K opcode_test [11:0] $end
$var wire 1 < rst $end
$var wire 32 L RS_ID2_VAL_test [31:0] $end
$var wire 32 M RS_ID1_VAL_test [31:0] $end
$var wire 32 N Immediate_test [31:0] $end
$var reg 1 - FULL_FLAG $end
$var reg 4 O FU_ALUOP [3:0] $end
$var reg 32 P FU_Immediate [31:0] $end
$var reg 4 Q FU_RS_ID [3:0] $end
$var reg 32 R FU_Val1 [31:0] $end
$var reg 32 S FU_Val2 [31:0] $end
$var reg 4 T Next_Free [3:0] $end
$var reg 4 U i [3:0] $end
$var reg 4 V j [3:0] $end
$var reg 4 W k [3:0] $end
$upscope $end
$upscope $end
$enddefinitions $end
$comment Show the parameter values. $end
$dumpall
$end
#0
$dumpvars
bx W
bx V
b0 U
b0 T
bx S
bx R
bx Q
bx P
bx O
bx N
bx M
bx L
bx K
bx J
bx I
bx H
bx G
bx F
bx E
bx D
bx C
bx B
bx A
bx @
bx ?
bx >
bx =
0<
bx ;
bx :
09
x8
bx 7
bx 6
bx 5
bx 4
bx 3
02
bx 1
bx 0
bx /
bx .
x-
bx ,
bx +
bx *
bx )
bx (
bx '
bx &
bx %
bx $
bx #
x"
bx !
$end
#1
b1000 V
19
#2
09
b1000 V
0-
b0 U
1<
#3
b0 U
b1000 V
19
#4
09
08
b1001101 3
b1001101 B
b110 7
b110 G
b101 5
b101 D
b100 6
b100 F
b11 4
b11 C
b10 /
b10 >
b1 ;
b1 J
0<
#5
b1000 V
19
#6
09
18
#7
b1000 U
b1000 T
b1000 V
19
#8
09
b1010111 3
b1010111 B
b10000 7
b10000 G
b1111 5
b1111 D
b110 6
b110 F
b101 4
b101 C
b1100 /
b1100 >
b1011 ;
b1011 J
08
#9
b1000 V
19
#10
09
18
#11
b1000 U
b111 T
b1000 V
19
#12
09
0"
b0 :
b0 I
b0 =
08
#13
b1000 V
19
#14
09
b1 :
b1 I
b1 =
#15
b1000 V
19
#16
09
b10 :
b10 I
b10 =
#17
b1000 V
19
#18
09
b11 :
b11 I
b11 =
#19
b1000 V
19
#20
09
b100 :
b100 I
b100 =
#21
b1000 V
19
#22
09
b101 :
b101 I
b101 =
#23
b1000 V
19
#24
09
b1111 &
b1111 M
b10000 $
b10000 L
b1010111 '
b1010111 N
b1011 !
b1011 K
b1100 .
b1100 ?
b101 %
b101 E
b110 #
b110 H
1"
b110 :
b110 I
b110 =
#25
b1000 V
19
#26
09
b101 &
b101 M
b110 $
b110 L
b1001101 '
b1001101 N
b1 !
b1 K
b10 .
b10 ?
b11 %
b11 E
b100 #
b100 H
b111 :
b111 I
b111 =
#27
b1000 V
19
#28
09
b1000 =
#29
b1000 V
19
#30
09
bx &
bx M
bx $
bx L
bx '
bx N
bx !
bx K
bx .
bx ?
bx %
bx E
bx #
bx H
0"
b0 :
b0 I
b0 =
#31
b1000 V
19
#32
09
b1 :
b1 I
b1 =
#33
b1000 V
19
#34
09
b10 :
b10 I
b10 =
#35
b1000 V
19
#36
09
b11 :
b11 I
b11 =
#37
b1000 V
19
#38
09
b100 :
b100 I
b100 =
#39
b1000 V
19
#40
09
b101 :
b101 I
b101 =
#41
b1000 V
19
#42
09
b1111 &
b1111 M
b10000 $
b10000 L
b1010111 '
b1010111 N
b1011 !
b1011 K
b1100 .
b1100 ?
b101 %
b101 E
b110 #
b110 H
1"
b110 :
b110 I
b110 =
#43
b1000 V
19
#44
09
b101 &
b101 M
b110 $
b110 L
b1001101 '
b1001101 N
b1 !
b1 K
b10 .
b10 ?
b11 %
b11 E
b100 #
b100 H
b111 :
b111 I
b111 =
#45
b1000 V
19
#46
09
12
b1000 =
#47
b1000 V
b1000 W
19
#48
09
bx &
bx M
bx $
bx L
bx '
bx N
bx !
bx K
bx .
bx ?
bx %
bx E
bx #
bx H
0"
b0 :
b0 I
b0 =
#49
b1000 W
b1000 V
19
#50
09
b1 :
b1 I
b1 =
#51
b1000 V
b1000 W
19
#52
09
b10 :
b10 I
b10 =
#53
b1000 W
b1000 V
19
#54
09
b11 :
b11 I
b11 =
#55
b1000 V
b1000 W
19
#56
09
b100 :
b100 I
b100 =
#57
b1000 W
b1000 V
19
#58
09
b101 :
b101 I
b101 =
#59
b1000 V
b1000 W
19
#60
09
b1111 &
b1111 M
b10000 $
b10000 L
b1010111 '
b1010111 N
b1011 !
b1011 K
b1100 .
b1100 ?
b101 %
b101 E
b110 #
b110 H
1"
b110 :
b110 I
b110 =
#61
b1000 W
b1000 V
19
#62
09
b101 &
b101 M
b110 $
b110 L
b1001101 '
b1001101 N
b1 !
b1 K
b10 .
b10 ?
b11 %
b11 E
b100 #
b100 H
b111 :
b111 I
b111 =
#63
b1000 V
b1000 W
19
#64
09
b1111011 1
b1111011 A
b101 0
b101 @
b1000 =
#65
b1000 W
b1000 V
19
#66
09
02
b111001000 1
b111001000 A
b110 0
b110 @
#67
b1000 V
19
#68
09
bx &
bx M
bx $
bx L
bx '
bx N
bx !
bx K
bx .
bx ?
bx %
bx E
bx #
bx H
0"
b0 :
b0 I
b0 =
#69
b1000 V
19
#70
09
b1 :
b1 I
b1 =
#71
b1000 V
19
#72
09
b10 :
b10 I
b10 =
#73
b1000 V
19
#74
09
b11 :
b11 I
b11 =
#75
b1000 V
19
#76
09
b100 :
b100 I
b100 =
#77
b1000 V
19
#78
09
b101 :
b101 I
b101 =
#79
b1000 V
19
#80
09
b1111011 &
b1111011 M
b111001000 $
b111001000 L
b1010111 '
b1010111 N
b1011 !
b1011 K
b1100 .
b1100 ?
b0 %
b0 E
b0 #
b0 H
1"
b110 :
b110 I
b110 =
#81
b1000 V
19
#82
09
b101 &
b101 M
b110 $
b110 L
b1001101 '
b1001101 N
b1 !
b1 K
b10 .
b10 ?
b11 %
b11 E
b100 #
b100 H
b111 :
b111 I
b111 =
#83
b1000 V
19
#84
09
12
b1000 =
#85
b1010111 +
b1010111 P
b111001000 (
b111001000 S
b1111011 )
b1111011 R
b1100 ,
b1100 O
b111 *
b111 Q
b1000 W
b1000 V
19
#86
09
bx &
bx M
bx $
bx L
bx '
bx N
bx !
bx K
bx .
bx ?
bx %
bx E
bx #
bx H
0"
b0 :
b0 I
b0 =
#87
b1000 V
b1000 W
19
#88
09
b1 :
b1 I
b1 =
#89
b1000 W
b1000 V
19
#90
09
b10 :
b10 I
b10 =
#91
b1000 V
b1000 W
19
#92
09
b11 :
b11 I
b11 =
#93
b1000 W
b1000 V
19
#94
09
b100 :
b100 I
b100 =
#95
b1000 V
b1000 W
19
#96
09
b101 :
b101 I
b101 =
#97
b1000 W
b1000 V
19
#98
09
b1111011 &
b1111011 M
b111001000 $
b111001000 L
b1010111 '
b1010111 N
b1011 !
b1011 K
b1100 .
b1100 ?
b0 %
b0 E
b0 #
b0 H
1"
b110 :
b110 I
b110 =
#99
b1000 V
b1000 W
19
#100
09
b101 &
b101 M
b110 $
b110 L
b1001101 '
b1001101 N
b1 !
b1 K
b10 .
b10 ?
b11 %
b11 E
b100 #
b100 H
b111 :
b111 I
b111 =
#101
b1000 W
b1000 V
19
#102
09
b1100010101 1
b1100010101 A
b11 0
b11 @
02
b1000 =
#103
b1100010101 &
b1100010101 M
b0 %
b0 E
b1000 V
19
#104
09
bx &
bx M
bx $
bx L
bx '
bx N
bx !
bx K
bx .
bx ?
bx %
bx E
bx #
bx H
0"
b0 :
b0 I
b0 =
#105
b1000 V
19
#106
09
b1 :
b1 I
b1 =
#107
b1000 V
19
#108
09
b10 :
b10 I
b10 =
#109
b1000 V
19
#110
09
b11 :
b11 I
b11 =
#111
b1000 V
19
#112
09
b100 :
b100 I
b100 =
#113
b1000 V
19
#114
09
b101 :
b101 I
b101 =
#115
b1000 V
19
#116
09
b1111011 &
b1111011 M
b111001000 $
b111001000 L
b1010111 '
b1010111 N
b1011 !
b1011 K
b1100 .
b1100 ?
b0 %
b0 E
b0 #
b0 H
1"
b110 :
b110 I
b110 =
#117
b1000 V
19
#118
09
b1100010101 &
b1100010101 M
b110 $
b110 L
b1001101 '
b1001101 N
b1 !
b1 K
b10 .
b10 ?
b100 #
b100 H
b111 :
b111 I
b111 =
#119
b1000 V
19
#120
09
b1111100111 1
b1111100111 A
b100 0
b100 @
b1000 =
#121
b1111100111 $
b1111100111 L
b0 #
b0 H
b1000 V
19
#122
09
bx &
bx M
bx $
bx L
bx '
bx N
bx !
bx K
bx .
bx ?
bx %
bx E
bx #
bx H
0"
b0 :
b0 I
b0 =
#123
b1000 V
19
#124
09
b1 :
b1 I
b1 =
#125
b1000 V
19
#126
09
b10 :
b10 I
b10 =
#127
b1000 V
19
#128
09
b11 :
b11 I
b11 =
#129
b1000 V
19
#130
09
b100 :
b100 I
b100 =
#131
b1000 V
19
#132
09
b101 :
b101 I
b101 =
#133
b1000 V
19
#134
09
b1111011 &
b1111011 M
b111001000 $
b111001000 L
b1010111 '
b1010111 N
b1011 !
b1011 K
b1100 .
b1100 ?
b0 %
b0 E
b0 #
b0 H
1"
b110 :
b110 I
b110 =
#135
b1000 V
19
#136
09
b1100010101 &
b1100010101 M
b1111100111 $
b1111100111 L
b1001101 '
b1001101 N
b1 !
b1 K
b10 .
b10 ?
b111 :
b111 I
b111 =
#137
b1000 V
19
#138
09
12
b1000 =
#139
b1000 V
b1001101 +
b1001101 P
b1111100111 (
b1111100111 S
b1100010101 )
b1100010101 R
b10 ,
b10 O
b1000 *
b1000 Q
b1000 W
19
#140
09
bx &
bx M
bx $
bx L
bx '
bx N
bx !
bx K
bx .
bx ?
bx %
bx E
bx #
bx H
0"
b0 :
b0 I
b0 =
#141
b1000 W
b1000 V
19
#142
09
b1 :
b1 I
b1 =
#143
b1000 V
b1000 W
19
#144
09
b10 :
b10 I
b10 =
#145
b1000 W
b1000 V
19
#146
09
b11 :
b11 I
b11 =
#147
b1000 V
b1000 W
19
#148
09
b100 :
b100 I
b100 =
#149
b1000 W
b1000 V
19
#150
09
b101 :
b101 I
b101 =
#151
b1000 V
b1000 W
19
#152
09
b1111011 &
b1111011 M
b111001000 $
b111001000 L
b1010111 '
b1010111 N
b1011 !
b1011 K
b1100 .
b1100 ?
b0 %
b0 E
b0 #
b0 H
b110 :
b110 I
b110 =
#153
b1000 W
b1000 V
19
#154
09
b1100010101 &
b1100010101 M
b1111100111 $
b1111100111 L
b1001101 '
b1001101 N
b1 !
b1 K
b10 .
b10 ?
1"
b111 :
b111 I
b111 =
#155
b1000 V
b1000 W
19
#156
09
02
b1000 =
#157
b1000 V
19
#158
09
bx &
bx M
bx $
bx L
bx '
bx N
bx !
bx K
bx .
bx ?
bx %
bx E
bx #
bx H
0"
b0 :
b0 I
b0 =
#159
b1000 V
19
#160
09
b1 :
b1 I
b1 =
#161
b1000 V
19
#162
09
b10 :
b10 I
b10 =
#163
b1000 V
19
#164
09
b11 :
b11 I
b11 =
#165
b1000 V
19
#166
09
b100 :
b100 I
b100 =
#167
b1000 V
19
#168
09
b101 :
b101 I
b101 =
#169
b1000 V
19
#170
09
b1111011 &
b1111011 M
b111001000 $
b111001000 L
b1010111 '
b1010111 N
b1011 !
b1011 K
b1100 .
b1100 ?
b0 %
b0 E
b0 #
b0 H
b110 :
b110 I
b110 =
#171
b1000 V
19
#172
09
b1100010101 &
b1100010101 M
b1111100111 $
b1111100111 L
b1001101 '
b1001101 N
b1 !
b1 K
b10 .
b10 ?
1"
b111 :
b111 I
b111 =
#173
b1000 V
19
#174
09
b0 6
b0 F
b0 4
b0 C
b1101111000 ;
b1101111000 J
b1000 =
#175
b1000 V
19
#176
09
bx &
bx M
bx $
bx L
bx '
bx N
bx !
bx K
bx .
bx ?
bx %
bx E
bx #
bx H
0"
b0 :
b0 I
b0 =
#177
b1000 V
19
#178
09
b1 :
b1 I
b1 =
#179
b1000 V
19
#180
09
b10 :
b10 I
b10 =
#181
b1000 V
19
#182
09
b11 :
b11 I
b11 =
#183
b1000 V
19
#184
09
b100 :
b100 I
b100 =
#185
b1000 V
19
#186
09
b101 :
b101 I
b101 =
#187
b1000 V
19
#188
09
b1111011 &
b1111011 M
b111001000 $
b111001000 L
b1010111 '
b1010111 N
b1011 !
b1011 K
b1100 .
b1100 ?
b0 %
b0 E
b0 #
b0 H
b110 :
b110 I
b110 =
#189
b1000 V
19
#190
09
b1100010101 &
b1100010101 M
b1111100111 $
b1111100111 L
b1001101 '
b1001101 N
b1 !
b1 K
b10 .
b10 ?
1"
b111 :
b111 I
b111 =
#191
b1000 V
19
#192
09
18
b1000 =
#193
b1000 V
b1000 U
b111 T
19
#194
09
bx &
bx M
bx $
bx L
bx '
bx N
bx !
bx K
bx .
bx ?
bx %
bx E
bx #
bx H
0"
b0 :
b0 I
b0 =
08
#195
b1000 V
19
#196
09
b1 :
b1 I
b1 =
#197
b1000 V
19
#198
09
b10 :
b10 I
b10 =
#199
b1000 V
19
#200
09
b11 :
b11 I
b11 =
#201
b1000 V
19
#202
09
b100 :
b100 I
b100 =
#203
b1000 V
19
#204
09
b101 :
b101 I
b101 =
#205
b1000 V
19
#206
09
b1111 &
b1111 M
b10000 $
b10000 L
b1010111 '
b1010111 N
b1101111000 !
b1101111000 K
b1100 .
b1100 ?
b0 %
b0 E
b0 #
b0 H
1"
b110 :
b110 I
b110 =
#207
b1000 V
19
#208
09
b1100010101 &
b1100010101 M
b1111100111 $
b1111100111 L
b1001101 '
b1001101 N
b1 !
b1 K
b10 .
b10 ?
b111 :
b111 I
b111 =
#209
b1000 V
19
#210
09
0"
12
b1000 =
#211
b1000 V
b1010111 +
b1010111 P
b10000 (
b10000 S
b1111 )
b1111 R
b1100 ,
b1100 O
b111 *
b111 Q
b1000 W
19
#212
09
bx &
bx M
bx $
bx L
bx '
bx N
bx !
bx K
bx .
bx ?
bx %
bx E
bx #
bx H
b0 :
b0 I
b0 =
#213
b1000 W
b1000 V
19
#214
09
b1 :
b1 I
b1 =
#215
b1000 V
b1000 W
19
#216
09
b10 :
b10 I
b10 =
#217
b1000 W
b1000 V
19
#218
09
b11 :
b11 I
b11 =
#219
b1000 V
b1000 W
19
#220
09
b100 :
b100 I
b100 =
#221
b1000 W
b1000 V
19
#222
09
b101 :
b101 I
b101 =
#223
b1000 V
b1000 W
19
#224
09
b1111 &
b1111 M
b10000 $
b10000 L
b1010111 '
b1010111 N
b1101111000 !
b1101111000 K
b1100 .
b1100 ?
b0 %
b0 E
b0 #
b0 H
1"
b110 :
b110 I
b110 =
#225
b1000 W
b1000 V
19
#226
09
b1100010101 &
b1100010101 M
b1111100111 $
b1111100111 L
b1001101 '
b1001101 N
b1 !
b1 K
b10 .
b10 ?
0"
b111 :
b111 I
b111 =
#227
b1000 V
b1000 W
19
#228
09
b1000 =
