SSOOO/AddressUnit&ld_st buffer/LdStBuffer.v



/*
inputs:
    - all of the AddressUnit outputs
internal registers:
    - busy bit and ready bit is needed
*/

module LdStBuffer
(
    input clk, rst,
    input VALID_Inst,
    input [4:0]  ROBEN,
    input [4:0]  Rd,
    input [11:0] opcode,
    input [4:0]  ROBEN1, ROBEN2,
    input [31:0] ROBEN1_VAL, ROBEN2_VAL,
    input [31:0] Immediate,
    input [31:0] EA, Write_Data,

    input [4:0] CDB_ROBEN,
    input [31:0] CDB_ROBEN_VAL,


    output reg out_VALID_Inst,
    output reg [4:0]  out_ROBEN,
    output reg [4:0]  out_Rd,
    output reg [11:0] out_opcode,
    output reg [4:0]  out_ROBEN1, out_ROBEN2,
    output reg [31:0] out_ROBEN1_VAL, out_ROBEN2_VAL,
    output reg [31:0] out_Immediate,
    output reg [31:0] out_EA, out_Write_Data,

    output reg [3:0] Start_Index,
    output reg [3:0] End_Index



    ,input  [4:0] index_test,    
    output Reg_Busy_test,
    output Reg_Ready_test,
    output [11:0] Reg_opcode_test,
    output [4:0] Reg_Rd_test,
    output [31:0] Reg_Write_Data_test,
    output [31:0] Reg_EA_test,
    output [4:0] Reg_ROBEN_test,
    output [4:0] Reg_ROBEN1_test,
    output [4:0] Reg_ROBEN2_test,
    output [31:0] Reg_ROBEN1_VAL_test,
    output [31:0] Reg_ROBEN2_VAL_test,
    output [31:0] Reg_Immediate_test
);




reg Reg_Busy [15:0];
wire Reg_Ready [15:0];

reg [11:0] Reg_opcode [15:0];
reg [4:0] Reg_Rd [15:0];
reg [31:0] Reg_Write_Data [15:0];
reg [31:0] Reg_EA [15:0];
reg [4:0] Reg_ROBEN [15:0];
reg [4:0] Reg_ROBEN1 [15:0];
reg [4:0] Reg_ROBEN2 [15:0];
reg [31:0] Reg_ROBEN1_VAL [15:0];
reg [31:0] Reg_ROBEN2_VAL [15:0];
reg [31:0] Reg_Immediate [15:0];

`define I(i) i[3:0]
`define readybit(i) assign Reg_Ready[i] = Reg_ROBEN1[i] == 0 && Reg_ROBEN2[i] == 0
`readybit(0);
`readybit(1);
`readybit(2);
`readybit(3);
`readybit(4);
`readybit(5);
`readybit(6);
`readybit(7);
`readybit(8);
`readybit(9);
`readybit(10);
`readybit(11);
`readybit(12);
`readybit(13);
`readybit(14);
`readybit(15);



assign Reg_Busy_test = Reg_Busy[`I(index_test)];
assign Reg_Ready_test = Reg_Ready[`I(index_test)];
assign Reg_opcode_test = Reg_opcode[`I(index_test)];
assign Reg_Rd_test = Reg_Rd[`I(index_test)];
assign Reg_Write_Data_test = Reg_Write_Data[`I(index_test)];
assign Reg_EA_test = Reg_EA[`I(index_test)];
assign Reg_ROBEN_test = Reg_ROBEN[`I(index_test)];
assign Reg_ROBEN1_test = Reg_ROBEN1[`I(index_test)];
assign Reg_ROBEN2_test = Reg_ROBEN2[`I(index_test)];
assign Reg_ROBEN1_VAL_test = Reg_ROBEN1_VAL[`I(index_test)];
assign Reg_ROBEN2_VAL_test = Reg_ROBEN2_VAL[`I(index_test)];
assign Reg_Immediate_test = Reg_Immediate[`I(index_test)];





reg [4:0] i = 0;
always@(posedge clk, posedge rst) begin
    if (rst) begin
        for (i = 0; i < 16; i = i + 1) begin
            Reg_Busy[`I(i)] = 0;
        end
        End_Index = 0;
    end
    else if (VALID_Inst) begin
        Reg_Busy[End_Index] = 1'b1;

        Reg_opcode[End_Index] = opcode;
        Reg_Rd[End_Index] = Rd;
        Reg_Write_Data[End_Index] = Write_Data;
        Reg_EA[End_Index] = EA;
        Reg_ROBEN[End_Index] = ROBEN;
        Reg_ROBEN1[End_Index] = ROBEN1;
        Reg_ROBEN2[End_Index] = ROBEN2;
        Reg_ROBEN1_VAL[End_Index] = ROBEN1_VAL;
        Reg_ROBEN2_VAL[End_Index] = ROBEN2_VAL;
        Reg_Immediate[End_Index] = Immediate;

        End_Index = End_Index + 1'b1;
    end
end




reg [4:0] j;
always@(posedge clk, posedge rst) begin
    for (j = 0; j < 16; j = j + 1) begin
        if (Reg_Busy[`I(j)]) begin
            if (Reg_ROBEN1[`I(j)] == CDB_ROBEN) begin
                Reg_ROBEN1_VAL[`I(j)] = CDB_ROBEN_VAL;
                Reg_ROBEN1[`I(j)] = 0;
            end
            if (Reg_ROBEN2[`I(j)] == CDB_ROBEN) begin
                Reg_ROBEN2_VAL[`I(j)] = CDB_ROBEN_VAL;
                Reg_ROBEN2[`I(j)] = 0;
            end
        end
    end
end


reg [4:0] k = 0;
always@(posedge clk, posedge rst) begin
    if (rst)
        Start_Index = 0;

    if (Reg_Busy[Start_Index] && Reg_Ready[Start_Index]) begin
        out_VALID_Inst = 1'b1;
        out_ROBEN = Reg_ROBEN[Start_Index];
        out_Rd = Reg_Rd[Start_Index];
        out_opcode = Reg_opcode[Start_Index];
        out_ROBEN1 = Reg_ROBEN1[Start_Index]; 
        out_ROBEN2 = Reg_ROBEN2[Start_Index];
        out_ROBEN1_VAL = Reg_ROBEN1_VAL[Start_Index]; 
        out_ROBEN2_VAL = Reg_ROBEN2_VAL[Start_Index];
        out_Immediate = Reg_Immediate[Start_Index];
        out_EA = Reg_EA[Start_Index]; 
        out_Write_Data = Reg_Write_Data[Start_Index];
        
        Reg_Busy[Start_Index] = 0;
        Start_Index = Start_Index + 1'b1;
    end
    else begin
        out_VALID_Inst = 1'b0;
    end
end



endmodule

SSOOO/AddressUnit&ld_st buffer/LdStBuffer_tb.v


`define HALF_CYCLE 1
`define ONE_CLK (2 * `HALF_CYCLE)
`define ADVANCE_N_CYCLE(N) #(`ONE_CLK * N);


`define DISPLAYVALS \
clk_en = 0; \
$display("Start_Index = %d, End_Index = %d", Start_Index, End_Index); \
$display("out_VALID_Inst = %d, out_ROBEN = %d, out_Rd = %d, out_opcode = %d, out_ROBEN1 = %d,  out_ROBEN2 = %d, out_ROBEN1_VAL = %d,  out_ROBEN2_VAL = %d, out_Immediate = %d, out_EA = %d,\nout_Write_Data = %d\n", \
        out_VALID_Inst, out_ROBEN, out_Rd, out_opcode, out_ROBEN1,  out_ROBEN2, out_ROBEN1_VAL,  out_ROBEN2_VAL, out_Immediate, out_EA, out_Write_Data); \
for (i = 0; i < 16; i = i + 1) begin \
    index_test = i[4:0]; \
    #`ONE_CLK $display("%-20s = %-4d\n%-20s = %-4d, %-20s = %-4d, %-20s = %-4h, %-20s = %-4d, %-20s = %-4d, %-20s = %-4d, \n%-20s = %-4d, %-20s = %-4d, %-20s = %-4d, %-20s = %-4d, %-20s = %-4d, %-20s = %-4d\n", \
    "index_test", index_test, "Reg_Busy_test", Reg_Busy_test, "Reg_Ready_test", Reg_Ready_test, "Reg_opcode_test", Reg_opcode_test, "Reg_Rd_test", Reg_Rd_test, "Reg_Write_Data_test", Reg_Write_Data_test, \
    "Reg_EA_test", Reg_EA_test, "Reg_ROBEN_test", Reg_ROBEN_test, "Reg_ROBEN1_test", Reg_ROBEN1_test, "Reg_ROBEN2_test", Reg_ROBEN2_test, "Reg_ROBEN1_VAL_test", Reg_ROBEN1_VAL_test, \
    "Reg_ROBEN2_VAL_test", Reg_ROBEN2_VAL_test, "Reg_Immediate_test", Reg_Immediate_test); \
end \
clk_en = 1; \
$display("\n\n");


`include "LdStBuffer.v"

module LoadBuffer_tb();



reg clk = 0, rst;
reg VALID_Inst;
reg [4:0]  ROBEN;
reg [4:0]  Rd;
reg [11:0] opcode;
reg [4:0]  ROBEN1, ROBEN2;
reg [31:0] ROBEN1_VAL, ROBEN2_VAL;
reg [31:0] Immediate;
reg [31:0] EA, Write_Data;
reg [4:0] CDB_ROBEN;
reg [31:0] CDB_ROBEN_VAL;


wire out_VALID_Inst;
wire [4:0]  out_ROBEN;
wire [4:0]  out_Rd;
wire [11:0] out_opcode;
wire [4:0]  out_ROBEN1, out_ROBEN2;
wire [31:0] out_ROBEN1_VAL, out_ROBEN2_VAL;
wire [31:0] out_Immediate;
wire [31:0] out_EA, out_Write_Data;

wire [3:0] Start_Index;
wire [3:0] End_Index;

reg  [4:0] index_test;
wire Reg_Busy_test;
wire Reg_Ready_test;
wire [11:0] Reg_opcode_test;
wire [4:0] Reg_Rd_test;
wire [31:0] Reg_Write_Data_test;
wire [31:0] Reg_EA_test;
wire [4:0] Reg_ROBEN_test;
wire [4:0] Reg_ROBEN1_test;
wire [4:0] Reg_ROBEN2_test;
wire [31:0] Reg_ROBEN1_VAL_test;
wire [31:0] Reg_ROBEN2_VAL_test;
wire [31:0] Reg_Immediate_test;




LdStBuffer dut
(
        .clk(clk), 
        .rst(rst),
        .VALID_Inst(VALID_Inst),
        .ROBEN(ROBEN),
        .Rd(Rd),
        .opcode(opcode),
        .ROBEN1(ROBEN1), 
        .ROBEN2(ROBEN2),
        .ROBEN1_VAL(ROBEN1_VAL), 
        .ROBEN2_VAL(ROBEN2_VAL),
        .Immediate(Immediate),
        .EA(EA), 
        .Write_Data(Write_Data),

        .CDB_ROBEN(CDB_ROBEN),
        .CDB_ROBEN_VAL(CDB_ROBEN_VAL),

        .out_VALID_Inst(out_VALID_Inst),
        .out_ROBEN(out_ROBEN),
        .out_Rd(out_Rd),
        .out_opcode(out_opcode),
        .out_ROBEN1(out_ROBEN1), 
        .out_ROBEN2(out_ROBEN2),
        .out_ROBEN1_VAL(out_ROBEN1_VAL), 
        .out_ROBEN2_VAL(out_ROBEN2_VAL),
        .out_Immediate(out_Immediate),
        .out_EA(out_EA), 
        .out_Write_Data(out_Write_Data),

        .Start_Index(Start_Index),
        .End_Index(End_Index),

        .index_test(index_test),    
        .Reg_Busy_test(Reg_Busy_test),
        .Reg_Ready_test(Reg_Ready_test),
        .Reg_opcode_test(Reg_opcode_test),
        .Reg_Rd_test(Reg_Rd_test),
        .Reg_Write_Data_test(Reg_Write_Data_test),
        .Reg_EA_test(Reg_EA_test),
        .Reg_ROBEN_test(Reg_ROBEN_test),
        .Reg_ROBEN1_test(Reg_ROBEN1_test),
        .Reg_ROBEN2_test(Reg_ROBEN2_test),
        .Reg_ROBEN1_VAL_test(Reg_ROBEN1_VAL_test),
        .Reg_ROBEN2_VAL_test(Reg_ROBEN2_VAL_test),
        .Reg_Immediate_test(Reg_Immediate_test)
);


reg clk_en = 0;
always begin
        #(`HALF_CYCLE) clk <= (~clk_en & clk) | (clk_en & ~clk);
end
integer i;
initial begin
$dumpfile("testout_LdStBuffer.vcd");
$dumpvars;

clk_en = 1;
rst = 0; `ADVANCE_N_CYCLE(1); rst = 1; `ADVANCE_N_CYCLE(1); rst = 0;

`DISPLAYVALS
// TODO: test it

$finish;

end


endmodule

SSOOO/AddressUnit&ld_st buffer/testout_LdStBuffer.vcd
$date
	Wed Dec 25 18:03:13 2024
$end
$version
	Icarus Verilog
$end
$timescale
	1s
$end
$scope module LoadBuffer_tb $end
$var wire 12 ! out_opcode [11:0] $end
$var wire 32 " out_Write_Data [31:0] $end
$var wire 1 # out_VALID_Inst $end
$var wire 5 $ out_Rd [4:0] $end
$var wire 32 % out_ROBEN2_VAL [31:0] $end
$var wire 5 & out_ROBEN2 [4:0] $end
$var wire 32 ' out_ROBEN1_VAL [31:0] $end
$var wire 5 ( out_ROBEN1 [4:0] $end
$var wire 5 ) out_ROBEN [4:0] $end
$var wire 32 * out_Immediate [31:0] $end
$var wire 32 + out_EA [31:0] $end
$var wire 4 , Start_Index [3:0] $end
$var wire 12 - Reg_opcode_test [11:0] $end
$var wire 32 . Reg_Write_Data_test [31:0] $end
$var wire 1 / Reg_Ready_test $end
$var wire 5 0 Reg_Rd_test [4:0] $end
$var wire 5 1 Reg_ROBEN_test [4:0] $end
$var wire 5 2 Reg_ROBEN2_test [4:0] $end
$var wire 32 3 Reg_ROBEN2_VAL_test [31:0] $end
$var wire 5 4 Reg_ROBEN1_test [4:0] $end
$var wire 32 5 Reg_ROBEN1_VAL_test [31:0] $end
$var wire 32 6 Reg_Immediate_test [31:0] $end
$var wire 32 7 Reg_EA_test [31:0] $end
$var wire 1 8 Reg_Busy_test $end
$var wire 4 9 End_Index [3:0] $end
$var reg 5 : CDB_ROBEN [4:0] $end
$var reg 32 ; CDB_ROBEN_VAL [31:0] $end
$var reg 32 < EA [31:0] $end
$var reg 32 = Immediate [31:0] $end
$var reg 5 > ROBEN [4:0] $end
$var reg 5 ? ROBEN1 [4:0] $end
$var reg 32 @ ROBEN1_VAL [31:0] $end
$var reg 5 A ROBEN2 [4:0] $end
$var reg 32 B ROBEN2_VAL [31:0] $end
$var reg 5 C Rd [4:0] $end
$var reg 1 D VALID_Inst $end
$var reg 32 E Write_Data [31:0] $end
$var reg 1 F clk $end
$var reg 1 G clk_en $end
$var reg 5 H index_test [4:0] $end
$var reg 12 I opcode [11:0] $end
$var reg 1 J rst $end
$var integer 32 K i [31:0] $end
$scope module dut $end
$var wire 5 L CDB_ROBEN [4:0] $end
$var wire 32 M CDB_ROBEN_VAL [31:0] $end
$var wire 32 N EA [31:0] $end
$var wire 32 O Immediate [31:0] $end
$var wire 5 P ROBEN [4:0] $end
$var wire 5 Q ROBEN1 [4:0] $end
$var wire 32 R ROBEN1_VAL [31:0] $end
$var wire 5 S ROBEN2 [4:0] $end
$var wire 32 T ROBEN2_VAL [31:0] $end
$var wire 5 U Rd [4:0] $end
$var wire 1 8 Reg_Busy_test $end
$var wire 32 V Reg_EA_test [31:0] $end
$var wire 32 W Reg_Immediate_test [31:0] $end
$var wire 32 X Reg_ROBEN1_VAL_test [31:0] $end
$var wire 5 Y Reg_ROBEN1_test [4:0] $end
$var wire 32 Z Reg_ROBEN2_VAL_test [31:0] $end
$var wire 5 [ Reg_ROBEN2_test [4:0] $end
$var wire 5 \ Reg_ROBEN_test [4:0] $end
$var wire 5 ] Reg_Rd_test [4:0] $end
$var wire 1 / Reg_Ready_test $end
$var wire 32 ^ Reg_Write_Data_test [31:0] $end
$var wire 12 _ Reg_opcode_test [11:0] $end
$var wire 1 D VALID_Inst $end
$var wire 32 ` Write_Data [31:0] $end
$var wire 1 F clk $end
$var wire 5 a index_test [4:0] $end
$var wire 12 b opcode [11:0] $end
$var wire 1 J rst $end
$var reg 4 c End_Index [3:0] $end
$var reg 4 d Start_Index [3:0] $end
$var reg 5 e i [4:0] $end
$var reg 5 f j [4:0] $end
$var reg 5 g k [4:0] $end
$var reg 32 h out_EA [31:0] $end
$var reg 32 i out_Immediate [31:0] $end
$var reg 5 j out_ROBEN [4:0] $end
$var reg 5 k out_ROBEN1 [4:0] $end
$var reg 32 l out_ROBEN1_VAL [31:0] $end
$var reg 5 m out_ROBEN2 [4:0] $end
$var reg 32 n out_ROBEN2_VAL [31:0] $end
$var reg 5 o out_Rd [4:0] $end
$var reg 1 # out_VALID_Inst $end
$var reg 32 p out_Write_Data [31:0] $end
$var reg 12 q out_opcode [11:0] $end
$upscope $end
$upscope $end
$enddefinitions $end
$comment Show the parameter values. $end
$dumpall
$end
#0
$dumpvars
bx q
bx p
bx o
bx n
bx m
bx l
bx k
bx j
bx i
bx h
b0 g
bx f
b0 e
bx d
bx c
bx b
bx a
bx `
bx _
bx ^
bx ]
bx \
bx [
bx Z
bx Y
bx X
bx W
bx V
bx U
bx T
bx S
bx R
bx Q
bx P
bx O
bx N
bx M
bx L
bx K
0J
bx I
bx H
1G
0F
bx E
xD
bx C
bx B
bx A
bx @
bx ?
bx >
bx =
bx <
bx ;
bx :
bx 9
x8
bx 7
bx 6
bx 5
bx 4
bx 3
bx 2
bx 1
bx 0
x/
bx .
bx -
bx ,
bx +
bx *
bx )
bx (
bx '
bx &
bx %
bx $
x#
bx "
bx !
$end
#1
b10000 f
0#
1F
#2
0F
b0 ,
b0 d
b10000 f
b0 9
b0 c
b10000 e
1J
#3
b10000 e
b10000 f
1F
#4
08
b0 H
b0 a
b0 K
0G
0J
#6
b1 H
b1 a
b1 K
#8
b10 H
b10 a
b10 K
#10
b11 H
b11 a
b11 K
#12
b100 H
b100 a
b100 K
#14
b101 H
b101 a
b101 K
#16
b110 H
b110 a
b110 K
#18
b111 H
b111 a
b111 K
#20
b1000 H
b1000 a
b1000 K
#22
b1001 H
b1001 a
b1001 K
#24
b1010 H
b1010 a
b1010 K
#26
b1011 H
b1011 a
b1011 K
#28
b1100 H
b1100 a
b1100 K
#30
b1101 H
b1101 a
b1101 K
#32
b1110 H
b1110 a
b1110 K
#34
b1111 H
b1111 a
b1111 K
#36
0F
1G
b10000 K
